Workbook

Sheet Main

Sheet Target
K2: SEO | L2: Engagement Campaigns | R2: SC + Paid Campaign Leads (Digital) | Y2: Local Campaigns
B3: # | C3: Week | D3: Start | E3: End | F3: Info | G3: MQL / Day | H3: MQL / WK | I3: Investors | J3: Entreprenuers | K3: Website | L3: Whatsapp | M3: SMS | N3: emails | O3: Newsletters | P3: Webinars | Q3: Vodex Phone | R3: YouTube | S3: LinkedIn | T3: Google | U3: Facebook | V3: Instagram | W3: x Twitter | X3: Others | Y3: Events | Z3: Networking | AA3: Others
C4: SPOC | K4: Anil | L4: Vinay | M4: Vinay | N4: Akshaya | O4: Akshaya | P4: Akshaya | Q4: Vinay | R4: Vinay | S4: Akshaya | T4: Akshaya | U4: Anil | V4: Anil | W4: Anil | Y4: Akshaya | Z4: Akshaya
B5: 1 | C5: Week 1 | D5: 29/12/2025 | E5: 46113 | G5: =H5/7 -> 45.714286 | H5: =SUM(K5:AF5) -> 320 | L5: =Calcs!H16 -> 210 | M5: =Calcs!J16 -> 35 | N5: =Calcs!L16 -> 70 | S5: 2 | T5: 3
B6: 2 | C6: Week 2 | D6: 46027 | E6: 46033 | G6: =H6/7 -> 49.285714 | H6: =SUM(K6:AF6) -> 345 | L6: =L5+10 -> 220 | M6: =M5+5 -> 40 | N6: =N5+10 -> 80 | S6: 2 | T6: 3
B7: 3 | C7: Week 3 | D7: =D6+7 -> 46034 | E7: =E6+7 -> 46040 | G7: =H7/7 -> 71.571429 | H7: =SUM(K7:AF7) -> 501 | L7: =L6+10 -> 230 | M7: =M6+5 -> 45 | N7: =N6+10 -> 90 | P7: =Calcs!P16 -> 10 | Q7: =Calcs!R16 -> 120 | S7: 3 | T7: 3
B8: 4 | C8: Week 4 | D8: =D7+7 -> 46041 | E8: =E7+7 -> 46047 | G8: =H8/7 -> 76.142857 | H8: =SUM(K8:AF8) -> 533 | L8: =L7+10 -> 240 | M8: =M7+5 -> 50 | N8: =N7+10 -> 100 | P8: =P7+1 -> 11 | Q8: =Q7+5 -> 125 | S8: 3 | T8: 4
B9: 5 | C9: Week 5 | D9: =D8+7 -> 46048 | E9: =E8+7 -> 46054 | G9: =H9/7 -> 80.714286 | H9: =SUM(K9:AF9) -> 565 | L9: =L8+10 -> 250 | M9: =M8+5 -> 55 | N9: =N8+10 -> 110 | O9: 1 | P9: =P8+1 -> 12 | Q9: =Q8+5 -> 130 | S9: 3 | T9: 4
B10: 6 | C10: Week 6 | D10: =D9+7 -> 46055 | E10: =E9+7 -> 46061 | G10: =H10/7 -> 85.285714 | H10: =SUM(K10:AF10) -> 597 | L10: =L9+10 -> 260 | M10: =M9+5 -> 60 | N10: =N9+10 -> 120 | O10: 1 | P10: =P9+1 -> 13 | Q10: =Q9+5 -> 135 | S10: 4 | T10: 4
B11: 7 | C11: Week 7 | D11: =D10+7 -> 46062 | E11: =E10+7 -> 46068 | G11: =H11/7 -> 89.857143 | H11: =SUM(K11:AF11) -> 629 | L11: =L10+10 -> 270 | M11: =M10+5 -> 65 | N11: =N10+10 -> 130 | O11: 1 | P11: =P10+1 -> 14 | Q11: =Q10+5 -> 140 | S11: 4 | T11: 5
B12: 8 | C12: Week 8 | D12: =D11+7 -> 46069 | E12: =E11+7 -> 46075 | G12: =H12/7 -> 94.285714 | H12: =SUM(K12:AF12) -> 660 | L12: =L11+10 -> 280 | M12: =M11+5 -> 70 | N12: =N11+10 -> 140 | O12: 1 | P12: =P11+1 -> 15 | Q12: =Q11+5 -> 145 | S12: 4 | T12: 5
B13: 9 | C13: Week 9 | D13: =D12+7 -> 46076 | E13: =E12+7 -> 46082 | G13: =H13/7 -> 98.714286 | H13: =SUM(K13:AF13) -> 691 | L13: =L12+10 -> 290 | M13: =M12+5 -> 75 | N13: =N12+10 -> 150 | O13: 1 | P13: =P12+1 -> 16 | Q13: =Q12+5 -> 150 | S13: 4 | T13: 5
B14: 10 | C14: Week 10 | D14: =D13+7 -> 46083 | E14: =E13+7 -> 46089 | G14: =H14/7 -> 103.14286 | H14: =SUM(K14:AF14) -> 722 | L14: =L13+10 -> 300 | M14: =M13+5 -> 80 | N14: =N13+10 -> 160 | O14: 1 | P14: =P13+1 -> 17 | Q14: =Q13+5 -> 155 | S14: 4 | T14: 5
B15: 11 | C15: Week 11 | D15: =D14+7 -> 46090 | E15: =E14+7 -> 46096 | G15: =H15/7 -> 107.57143 | H15: =SUM(K15:AF15) -> 753 | L15: =L14+10 -> 310 | M15: =M14+5 -> 85 | N15: =N14+10 -> 170 | O15: 1 | P15: =P14+1 -> 18 | Q15: =Q14+5 -> 160 | S15: 4 | T15: 5
B16: 12 | C16: Week 12 | D16: =D15+7 -> 46097 | E16: =E15+7 -> 46103 | G16: =H16/7 -> 111 | H16: =SUM(K16:AF16) -> 777 | L16: =L15+10 -> 320 | M16: =M15+5 -> 90 | N16: =N15+10 -> 180 | O16: 3 | P16: =P15+1 -> 19 | Q16: =Q15+5 -> 165
B17: 13 | C17: Week 13 | D17: =D16+7 -> 46104 | E17: =E16+7 -> 46110 | G17: =H17/7 -> 115.42857 | H17: =SUM(K17:AF17) -> 808 | L17: =L16+10 -> 330 | M17: =M16+5 -> 95 | N17: =N16+10 -> 190 | O17: 3 | P17: =P16+1 -> 20 | Q17: =Q16+5 -> 170
B18: 14 | C18: Week 14 | D18: =D17+7 -> 46111 | E18: =E17+7 -> 46117 | G18: =H18/7 -> 119.85714 | H18: =SUM(K18:AF18) -> 839 | L18: =L17+10 -> 340 | M18: =M17+5 -> 100 | N18: =N17+10 -> 200 | O18: 3 | P18: =P17+1 -> 21 | Q18: =Q17+5 -> 175
B19: 15 | C19: Week 15 | D19: =D18+7 -> 46118 | E19: =E18+7 -> 46124 | G19: =H19/7 -> 124.28571 | H19: =SUM(K19:AF19) -> 870 | L19: =L18+10 -> 350 | M19: =M18+5 -> 105 | N19: =N18+10 -> 210 | O19: 3 | P19: =P18+1 -> 22 | Q19: =Q18+5 -> 180
B20: 16 | C20: Week 16 | D20: =D19+7 -> 46125 | E20: =E19+7 -> 46131 | G20: =H20/7 -> 128.85714 | H20: =SUM(K20:AF20) -> 902 | L20: =L19+10 -> 360 | M20: =M19+5 -> 110 | N20: =N19+10 -> 220 | O20: 4 | P20: =P19+1 -> 23 | Q20: =Q19+5 -> 185
B21: 17 | C21: Week 17 | D21: =D20+7 -> 46132 | E21: =E20+7 -> 46138 | G21: =H21/7 -> 133.28571 | H21: =SUM(K21:AF21) -> 933 | L21: =L20+10 -> 370 | M21: =M20+5 -> 115 | N21: =N20+10 -> 230 | O21: 4 | P21: =P20+1 -> 24 | Q21: =Q20+5 -> 190
B22: 18 | C22: Week 18 | D22: =D21+7 -> 46139 | E22: =E21+7 -> 46145 | G22: =H22/7 -> 137.71429 | H22: =SUM(K22:AF22) -> 964 | L22: =L21+10 -> 380 | M22: =M21+5 -> 120 | N22: =N21+10 -> 240 | O22: 4 | P22: =P21+1 -> 25 | Q22: =Q21+5 -> 195
B23: 19 | C23: Week 19 | D23: =D22+7 -> 46146 | E23: =E22+7 -> 46152 | G23: =H23/7 -> 142.14286 | H23: =SUM(K23:AF23) -> 995 | L23: =L22+10 -> 390 | M23: =M22+5 -> 125 | N23: =N22+10 -> 250 | O23: 4 | P23: =P22+1 -> 26 | Q23: =Q22+5 -> 200
B24: 20 | C24: Week 20 | D24: =D23+7 -> 46153 | E24: =E23+7 -> 46159 | G24: =H24/7 -> 146.71429 | H24: =SUM(K24:AF24) -> 1027 | L24: =L23+10 -> 400 | M24: =M23+5 -> 130 | N24: =N23+10 -> 260 | O24: 5 | P24: =P23+1 -> 27 | Q24: =Q23+5 -> 205
B25: 21 | C25: Week 21 | D25: =D24+7 -> 46160 | E25: =E24+7 -> 46166 | G25: =H25/7 -> 151.14286 | H25: =SUM(K25:AF25) -> 1058 | L25: =L24+10 -> 410 | M25: =M24+5 -> 135 | N25: =N24+10 -> 270 | O25: 5 | P25: =P24+1 -> 28 | Q25: =Q24+5 -> 210
B26: 22 | C26: Week 22 | D26: =D25+7 -> 46167 | E26: =E25+7 -> 46173 | G26: =H26/7 -> 155.57143 | H26: =SUM(K26:AF26) -> 1089 | L26: =L25+10 -> 420 | M26: =M25+5 -> 140 | N26: =N25+10 -> 280 | O26: 5 | P26: =P25+1 -> 29 | Q26: =Q25+5 -> 215
B27: 23 | C27: Week 23 | D27: =D26+7 -> 46174 | E27: =E26+7 -> 46180 | G27: =H27/7 -> 160 | H27: =SUM(K27:AF27) -> 1120 | L27: =L26+10 -> 430 | M27: =M26+5 -> 145 | N27: =N26+10 -> 290 | O27: 5 | P27: =P26+1 -> 30 | Q27: =Q26+5 -> 220
G28: =H28/7 -> 164.57143 | H28: =SUM(K28:AF28) -> 1152 | L28: =L27+10 -> 440 | M28: =M27+5 -> 150 | N28: =N27+10 -> 300 | O28: 6 | P28: =P27+1 -> 31 | Q28: =Q27+5 -> 225
L29: =L28+10 -> 450 | M29: =M28+5 -> 155 | N29: =N28+10 -> 310 | O29: 6 | P29: =P28+1 -> 32 | Q29: =Q28+5 -> 230

Sheet Report
E1: Visitors | H1: Leads
B2: Week | C2: Start Date | D2: End Date | E2: # Visitors | F2: SEO | G2: PPC Campaign | H2: MQL | I2: SEO | J2: PPC Campaign
B3: Week 1 | C3: 29/12/2025 | D3: 46113
B4: Week 2 | C4: 46027 | D4: 46033
B5: Week 3 | C5: =C4+7 -> 46034 | D5: =D4+7 -> 46040
B6: Week 4 | C6: =C5+7 -> 46041 | D6: =D5+7 -> 46047
B7: Week 5 | C7: =C6+7 -> 46048 | D7: =D6+7 -> 46054
B8: Week 6 | C8: =C7+7 -> 46055 | D8: =D7+7 -> 46061
B9: Week 7 | C9: =C8+7 -> 46062 | D9: =D8+7 -> 46068
B10: Week 8 | C10: =C9+7 -> 46069 | D10: =D9+7 -> 46075
B11: Week 9 | C11: =C10+7 -> 46076 | D11: =D10+7 -> 46082
B12: Week 10 | C12: =C11+7 -> 46083 | D12: =D11+7 -> 46089
B13: Week 11 | C13: =C12+7 -> 46090 | D13: =D12+7 -> 46096
B14: Week 12 | C14: =C13+7 -> 46097 | D14: =D13+7 -> 46103
B15: Week 13 | C15: =C14+7 -> 46104 | D15: =D14+7 -> 46110
B16: Week 14 | C16: =C15+7 -> 46111 | D16: =D15+7 -> 46117
... B25: Week 23 | C25: =C24+7 -> 46174 | D25: =D24+7 -> 46180

Sheet Calcs
B2: 7 Days Campaign | I2: 1st TPs - New Contacts | R2: # minutes
B3: Weekend rota | D3: Hrs | F3: Total | H3: WhatsApp | I3: SMS | J3: SMS | K3: emails | L3: emails | N3: News letter | P3: Webinars | R3: Vodex AI
C4: Day | D4: 8 | H4: 1000 | J4: 500 | L4: 1000 | N4: 300 | R4: 200
C5: Per Week | E5: 7 | H5: =H4*E5 -> 7000 | J5: =J4*$E$5 -> 3500 | L5: =L4*E5 -> 7000 | P5: 100 | R5: =R4*E5 -> 1400
C6: Per Month | E6: 4 | H6: =H5*E6 -> 28000 | J6: =J5*E6 -> 14000 | L6: =L5*E6 -> 28000 | P6: =P5*E6 -> 400 | R6: =R5*E6 -> 5600
C8: Data is relevant
B10: Success Rate
C11: Open Rate | D11: 85 - 98 % | E11: 0.9 | H11: =$H$6*E11 -> 25200
C12: CTA Button Click | D12: 5- 12% | E12: 0.08 | H12: =$H$6*E12 -> 2240
B13: 1 | C13: Leads (Best Case) | D13: 6 - 14% | E13: 0.1 | H13: =$H$6*E13 -> 2800 | I13: 0.04 | O13: 0.25 | Q13: 0.3
B14: 2 | C14: Leads (Practical) | E14: 0.06 | H14: =H6*E14 -> 1680 | I14: 0.02
B15: 3 | C15: Leads (Worst Case) | E15: 0.03 | H15: =H6*E15 -> 840 | I15: 0.01 | J15: =J6*I15 -> 140 | K15: 0.01 | L15: =L6*K15 -> 280 | M15: 0.01 | N15: =N4*M15 -> 3 | O15: 0.1 | P15: =P6*O15 -> 40 | Q15: 0.15 | R15: =R6*Q15 -> 840
C16: Per Week | H16: =H15/4 -> 210 | J16: =J15/4 -> 35 | L16: =L15/4 -> 70 | N16: =N15/4 -> 0.75 | P16: =P15/4 -> 10 | R16: =R15/7 -> 120
C17: per Day | H17: =H16/7 -> 30 | I17: =I16/7 -> 0 | J17: =J16/7 -> 5 | K17: =K16/7 -> 0 | L17: =L16/7 -> 10 | N17: =N16/7 -> 0.10714286 | R17: =R16/7 -> 17.142857
C23: Rate
C24: How many Tools

Sheet SEO
A2: A | B2: ON-page optimisation | C2: Start | D2: Status | E2: Ranking | F2: Notes
A3: 1 | B3: Website Analysis | C3: 45972 | D3: Done
A4: 2 | B4: Keyword Research | C4: 25/11/2025 | D4: Done
A5: 3 | B5: Competition Analysis | C5: 24/11/2025 | D5: Done
A6: 4 | B6: Backlink Analysis | C6: 23/12/2025 | D6: In progress
A7: 5 | B7: Initial Ranking Report | C7: NO | D7: NO
A8: 6 | B8: Website Structure Optimization | C8: NO | D8: NO
A9: 7 | B9: Meta tag Creation & Optimization | C9: 27/11/2025 | D9: Done
A10: 8 | B10: Headings Optimization (h1 & h2) | C10: 45912 | D10: Done
A11: 9 | B11: Urls Optimization | C11: NO | D11: NO
A12: 10 | B12: Images Optimization | C12: 45912 | D12: Done
A13: 11 | B13: XML Sitemap Creation | C13: 46003 | D13: Done
A14: 12 | B14: Robots.txt Optimization
A15: 13
A16: 14
A17: 15
A18: 16 | B18: OFF-page optimisation | C18: 22/12/2025 | D18: In progress
A19: 17 | B19: Directory submissions.
A20: 18 | B20: Social Bookmaking Submissions.
A21: 19 | B21: Article Submissions
A22: 20 | B22: Press Release Submissions
A23: 21 | B23: Blog Submissions.
A24: 22 | B24: One Way back links with mix PR
A25: 23
A26: 24
A27: 25
A28: 26
A29: 27
A30: 28

Sheet approach
P3: Approach | Q3: Unsuccessful | R3: Sucessful
C5: Concerns around hitting Targets / Success Rate | P5: 1st Touch point | Q5: Whatsapp | R5: STOP
C7: Data | P7: 2nd Touch point | Q7: SMS | R7: STOP
E8: Relevance of the Data | I8: Ensure the data is relevant
I9: Properly classified | P9: 3rd Touch point | Q9: email | R9: STOP
I10: Review every campaign to ensure the data quality
P11: 4th Touch Point | Q11: Repeat -Comms
C13: Tools and Limits | P13: 5th Touch Point | Q13: Vodex
E15: Limitations on # messages | I15: Use Multimple Tools | P15: 6th Touch Point - Final | Q15: Telesales
I16: Don't depend on one tool eg. GupShup,
I17: Try other althernative 3 to 5 Tools
C19: Content
E20: User for CTA - clicks | I20: Offers, Knowledge, use ful info
I21: Create Sense of urgency
I22: Bring reference
C25: Specific - touch points
E27: Connecting Dots | I27: Variables saved in the system
I28: Dates, Number of touches
I29: Clicks
I30: Calendar invitations
I31: Tickets for events
I32: Webinar links
I33: ✅ Education-led emails (not selling)
I34: ✅ Market insights / deal notes
I35: ✅ Founder POV / credibility stories
I36: ✅ Event invitations (webinars, dinners)
I37: ✅ Case studies (compliance-safe)
I38: ✅ Soft CTA → WhatsApp / Call

Sheet Tools
A1: # | B1: Tool | C1: Particulars | D1: Classification | E1: Campaigns | F1: SPOC | G1: Backup | H1: URL | I1: User Name | J1: PW | K1: Account / Ref | L1: Cost - Set up | M1: Cost - Per month | N1: Cost - Variable | O1: Notes
A2: 1 | B2: GupShup | D2: Comms | E2: WhatsApp, SMS, Insta, email, SC | F2: Vinay
A3: 2 | B3: Brevo | E3: WhatsApp, emails | F3: Team
A4: 3 | B4: Zoho | E4: SMS, Emails, | F4: Team
A5: 4 | B5: Hubspot | F5: Team
A6: 5 | B6: SEO Tool Add | C6: SEM Rush, AI tools | F6: Team
A7: 6 | B7: Google Analytics | F7: Team
A8: 7 | B8: Google Search Console | F8: Team
A9: 8 | B9: Vodex | F9: Vinay
A10: 9 | B10: Holo | C10: Content and Design AI | F10: Gayatri | H10: https://tryholo.ai/
A11: 10 | B11: Canva | D11: Design | F11: Anil Raj
A12: 11 | B12: Adobe Premium | D12: Design | F12: Team 1
A13: 12 | B13: ChatGPT Enterprise/ Paid | D13: Content, Design + | F13: Team
A14: 13
A15: 14
A16: 15
A17: 16
A18: 17
A19: 18
A20: 19
A21: 20
A22: 21
A23: 22
A24: 23
A25: 24
A26: 25

Sheet Action Items
A1: # | B1: Task | C1: Particulars | D1: Owner | E1: Start Date | F1: Due Date | G1: Status | H1: Notes
A2: 1 | B2: Keyword analysis | C2: Top 20 Keywords, competiton and full analysis | D2: Anil
A3: 2 | B3: WEBSITE – Mktg page builders
A4: 3 | B4: Landing pages
A5: 4 | B5: Squeeze pages
A6: 5 | B6: Sales pages
A7: 6 | B7: Thank you pages
A8: 7 | B8: Product Launch pages
A9: 8 | B9: Checkout pages
A10: 9 | B10: Video Sales letter pages
A11: 10 | B11: Membership portal builders
A12: 11 | B12: Shopping carts
A13: 12 | B13: Online form builders
A14: 13 | B14: Split testing and link tracking
... A16: 15 | B16: AI Marketing Stack
A17: 16 | B17: Marketing Analytics Stack | C17: SEO Adda 40 + tools
A18: 17 | B18: Graphics & Designs AI stack
A19: 18 | B19: Vodex platform live
A20: 19 | B20: Whatsapp live
A21: 20
A22: 21
A23: 22
A24: 23
A25: 24
A26: 25
A27: 26

Sheet SEO Adda Tools

Sheet SEO On-page
A1: Pages | B1: Keywords | C1: Title Tag | D1: Meta Description
A2: https://ritzgroup.co/ | B2: Best Investment Company in India , Ritz Group | C2: Best Investment Company in India | Ritz Group | D2: Ritz Group – Best Investment Company in India offering Venture Capital, Fund Management, Investors Club, and Micro & Macro Investment services.
A3: https://ritzgroup.co/venture-capital | B3: Top Venture Capital Firms in India 2025 , Ritz Group | C3: Top Venture Capital Firms in India 2025 | Ritz Group | D3: Discover why Ritz Group ranks among the top venture capital firms in India 2025, empowering startups with expert fund management, private equity, and investment growth.
A4: https://ritzgroup.co/fund-management | B4: Fund Management services in India , Ritz Group | C4: Fund Management services in India - Ritz Group | D4: Ritz Group stands among Fund Management services in India, offering expert fund management, portfolio growth, and venture capital solutions.
A5: https://ritzgroup.co/investors-club | B5: Business Investors in India , Investors Clubs | C5: Business Investors in India | Investors Clubs | D5: Discover leading business investors in India and exclusive investors clubs by Ritz Group, offering startup funding, venture capital, and investment growth.
A6: https://ritzgroup.co/micro-and-macro-investment | B6: Micro & Macro Investments in India , RitzGroup | C6: Micro & Macro Investments in India | RitzGroup | D6: Explore smart micro and macro investment opportunities in India with RitzGroup. Start small, grow steadily, and secure your financial future expert guidance.

Sheet Trending Keywords
A1: No | B1: Keyword | C1: Search Volume | D1: SEO Difficulty
A2: 1 | B2: best investment companies in india | C2: 480 | D2: 34
A3: 2 | B3: top 20 investment companies in india | C3: 590 | D3: 33
A4: 3 | B4: best company in india for investment | C4: 480 | D4: 12
A5: 4 | B5: best alternative investment funds in india | C5: 320 | D5: 22
A6: 5 | B6: top investment banking companies in india | C6: 320 | D6: 29
A7: 6 | B7: top 10 housing finance companies in india 2024 | C7: 110 | D7: 7
A8: 7 | B8: best investment companies in the world | C8: 90 | D8: 12
A9: 8 | B9: best investment plan in india for 5 years | C9: 70 | D9: 29
A10: 9 | B10: top 100 finance companies in india pdf | C10: 70 | D10: 6
A11: 10 | B11: best micro finance company in india | C11: 70 | D11: 10
A12: 11 | B12: best sip investment company in india | C12: 50 | D12: 26
A13: 12 | B13: best investment plan for 3 years in india | C13: 50 | D13: 26
... A47: 46 | B47: top investment holding companies in india | C47: 10 | D47: 5
B49: venture capital
A50: No | B50: Keyword | C50: Search Volume | D50: SEO Difficulty
A51: 1 | B51: top venture capital firms in india | C51: 1000 | D51: 25
A52: 2 | B52: top venture capitalists in india | C52: 1300 | D52: 30
A53: 3 | B53: top investment firms in india | C53: 140 | D53: 9
A54: 4 | B54: top venture capital firms in bangalore | C54: 50 | D54: 5
A55: 5 | B55: top seed funding companies in india | C55: 40 | D55: 7
A56: 6 | B56: top venture capital firms in mumbai | C56: 20 | D56: 5
A57: 7 | B57: highest paying venture capital firms in india | C57: 0 | D57: 4
A58: 8 | B58: top venture capital firms in delhi | C58: 0 | D58: 4
A59: 9 | B59: top 5 venture capitalists in india | C59: 0 | D59: 4
A60: 10 | B60: top investment companies in india for long term | C60: 0 | D60: 4
A61: 11 | B61: Top Venture Capital Firms & Investors in India in 2025 | C61: 0 | D61: 4
B63: Fund Management
A64: No | B64: Keyword | C64: Search Volume | D64: SEO Difficulty
A65: 1 | B65: fund management india | C65: 320 | D65: 20
A66: 2 | B66: mutual funds in india top 10 | C66: 5400 | D66: 27
A67: 3 | B67: investment management companies india | C67: 1600 | D67: 9
A68: 4 | B68: mutual funds in india comparison | C68: 1600 | D68: 9
A69: 5 | B69: etf funds in india list | C69: 880 | D69: 51
A70: 6 | B70: fund management companies | C70: 880 | D70: 51
A71: 7 | B71: fund manager salary in india | C71: 590 | D71: 33
A72: 8 | B72: invesco asset management india private limited | C72: 590 | D72: 7
A73: 9 | B73: innovations investment management india private limited | C73: 590 | D73: 18
A74: 10 | B74: mutual funds in india with best returns | C74: 590 | D74: 17
A75: 11 | B75: asset management company india | C75: 480 | D75: 9
A76: 12 | B76: provident fund in india rules | C76: 480 | D76: 48
... A97: 33 | B97: mutual fund in india regulated by | C97: 50 | D97: 5
B99: Investors Clubs
A100: No | B100: Keyword | C100: Search Volume | D100: SEO Difficulty
A101: 1 | B101: business investors club india | C101: 0 | D101: 4
A102: 2 | B102: property investors network india | C102: 0 | D102: 4
A103: 3 | B103: startup investment club india | C103: 0 | D103: 4
A104: 4 | B104: startup india wiki | C104: 260 | D104: 43
A105: 5 | B105: startup india 80 iac tax exemption | C105: 210 | D105: 5
A106: 6 | B106: business investors in india | C106: 170 | D106: 15
A107: 7 | B107: value investors club india | C107: 50 | D107: 8
A108: 8 | B108: startup investment india | C108: 40 | D108: 23
A109: 9 | B109: property investors in mumbai | C109: 30 | D109: 11
A110: 10 | B110: property news india | C110: 30 | D110: 13
A111: 11 | B111: property share india | C111: 30 | D111: 24
A112: 12 | B112: startup india kit | C112: 30 | D112: 13
... A125: 25 | B125: business clubs in hyderabad | C125: 0 | D125: 4
B127: Micro and Macro Investment
A128: No | B128: Keyword | C128: Search Volume | D128: SEO Difficulty
A129: 1 | B129: macro economic trends investing india | C129: 0 | D129: 4
A130: 2 | B130: best investment opportunities in india | C130: 90 | D130: 16
A131: 3 | B131: best business ideas in india 2024 | C131: 170 | D131: 5
A132: 4 | B132: where can i invest 1000 rupees | C132: 140 | D132: 15
A133: 5 | B133: best business ideas in india in hindi | C133: 140 | D133: 5
A134: 6 | B134: best safe investment options in india | C134: 140 | D134: 26
A135: 7 | B135: best business in india today | C135: 110 | D135: 13
A136: 8 | B136: best investment opportunity in india | C136: 90 | D136: 16
A137: 9 | B137: best money investment options in india | C137: 90 | D137: 21
A138: 10 | B138: best investment options for young adults in india | C138: 90 | D138: 18
A139: 11 | B139: which is best for invest money | C139: 40 | D139: 21
A140: 12 | B140: best investment for 6 months in india | C140: 30 | D140: 21
... A155: 27 | B155: best investment options in india for 5 years | C155: 0 | D155: 4
A157: No | B157: Keyword | C157: SEO Difficulty
A158: 1 | B158: green tech projects india | C158: 4
A159: 2 | B159: sustainable technology projects india | C159: 4
A160: 3 | B160: green technology investment india | C160: 4
A161: 4 | B161: fintech projects india | C161: 12
A162: 5 | B162: financial technology innovation india | C162: 4
A163: 6 | B163: digital payments projects india | C163: 4
A164: 7 | B164: healthtech projects india | C164: 12
A165: 8 | B165: healthcare technology startup india | C165: 4
A166: 9 | B166: telemedicine projects india | C166: 12
A167: 10 | B167: wellness lifestyle projects india | C167: 4
A168: 11 | B168: fashion & lifestyle startup india | C168: 4
A169: 12 | B169: lifestyle technology projects india | C169: 4
... A191: 34 | B191: impact investment projects india | C191: 4

Sheet Ritz keywords
A1: Key words
A2: Best Investment Company in India
A3: Top Venture Capital Firms in India 2025
A4: Fund Management services in India
A5: Business Investors in India | Investors Clubs
A6: Micro & Macro Investments in India
A7: Ritz Group – GreenTech, FinTech & HealthTech Investments

Sheet SE0 Off - page backlinks
A1: Date | B1: Referring URl | C1: DA | D1: PA | E1: Type of Submission | F1: Submitted URl | G1: Status
A2: 23/12/2025 | B2: Profile submission
B3: https://www.ranker.com/ | C3: 95 | D3: 85 | E3: Profile Creation | F3: https://www.ranker.com/writer/ritz-group
B4: https://devfolio.co/ | C4: 76 | D4: 64 | E4: Profile Creation | F4: https://devfolio.co/@Ritzgroup
B5: https://www.atlasobscura.com/ | C5: 83 | D5: 68 | E5: Profile Creation | F5: https://www.atlasobscura.com/users/9f4f3c46-ee34-4a9b-bd72-61cffd6b8ab8
B6: https://www.answers.com/ | C6: 15 | D6: 24 | E6: Profile Creation | F6: https://www.answers.com/u/ritzgroup
B7: https://www.indiegogo.com/ | C7: 90 | D7: 70 | E7: Profile Creation | F7: https://www.indiegogo.com/en/profile/ritz12345#/overview
B8: https://bookmarkrange.com/ | C8: 54 | D8: 45 | E8: Profile Creation | F8: https://bookmarkrange.com/user/ritzgroup1122
B9: https://www.pinterest.com/ | C9: 35 | D9: 56 | E9: Profile Creation | F9: https://www.pinterest.com/ritzgroupco123/
B10: SBMS Submission
B11: https://bookmarkrange.com/ | C11: 11 | D11: 42 | E11: SBMS | F11: https://bookmarkrange.com/story22617237/how-to-choose-the-right-investment-company-for-long-term-wealth-growth
B12: https://bookmarkbirth.com/ | C12: 15 | D12: 40 | E12: SBMS | F12: https://bookmarkbirth.com/story21340511/how-to-choose-the-right-investment-company-for-long-term-wealth-growth
B13: https://www.bookmarkfeeds.com | C13: 55 | D13: 64 | E13: SBMS | F13: https://www.bookmarkfeeds.com/preview-article/
B14: https://www.socialbookmarknow.info/ | C14: 18 | D14: 41 | E14: SBMS | F14: https://www.socialbookmarknow.info/preview-article/
B15: https://www.publicbuysell.com/ | C15: 42 | D15: 55 | E15: SBMS | F15: https://www.publicbuysell.com/preview-post/
B16: Directory Submission
B17: https://caida.eu/ | C17: 17 | D17: 45 | E17: Directories | F17: https://caida.eu/submit.php
B18: https://www.fire-directory.com/ | C18: 32 | D18: 51 | E18: Directories | F18: https://www.fire-directory.com/submit.php
B19: https://www.craigslist.org/ | C19: 88 | D19: 76 | E19: Directories | F19: https://hyderabad.craigslist.org/fns/d/how-to-choose-the-right-investment/7904178770.html
B20: https://linkdirectorylistings.org/ | C20: 73 | D20: 42 | E20: Directories | F20: https://linkdirectorylistings.org/submit-site/
B21: https://www.dizila.com/ | C21: 17 | D21: 45 | E21: Directories | F21: https://www.dizila.com/submit?c=27&LINK_TYPE=1
B22: Classifieds
B23: https://www.locanto.org | C23: 15 | D23: 23 | E23: Clasifieds | F23: https://www.locanto.org/nanakramguda/ID_8111869115/How-to-Choose-the-Right-Investment-Company-for-Long-Term-Wealth.html
B24: https://www.freeclassifiedssites.com/ | C24: 29 | D24: 50 | E24: Clasifieds | F24: https://www.freeclassifiedssites.com/index.php?view=post&cityid=609&lang=en&catid=12&subcatid=82&shortcutregion=&
B25: https://hyderabad.indads.in/ | C25: 20 | D25: 34 | E25: Clasifieds | F25: https://hyderabad.indads.in/item/1370065/
B26: https://hyderabad.classifiedsfactor.com/ | C26: 26 | D26: 29 | E26: Clasifieds | F26: https://items.classifiedsfactor.com/post-a-classified-ad-type.php
B27: https://www.advertiseera.com | C27: 22 | D27: 44 | E27: Clasifieds | F27: https://www.advertiseera.com/post-an-ad-step-6.php
A29: 24/12/2025 | B29: Profile submission
B30: https://justpaste.it/ | C30: 76 | D30: 64 | E30: Profile Creation | F30: https://justpaste.it/u/Ritzgroup1122
B31: https://medium.com/ | C31: 83 | D31: 68 | E31: Profile Creation | F31: https://medium.com/@ritzgroupco123
B32: https://dev.to/ | C32: 83 | D32: 68 | E32: Profile Creation | F32: https://dev.to/ritz_group_00b92b8a0f04df
B33: https://www.spreaker.com | C33: 90 | D33: 70 | E33: Profile Creation | F33: https://www.spreaker.com/user/ritz-group--18836066
B34: www.gitlab.com | C34: 92 | D34: 66 | E34: Profile Creation | F34: https://gitlab.com/ritzgroupco123
B35: https://altbookmark.com/ | C35: 15 | D35: 37 | E35: Profile Creation | F35: https://altbookmark.com/user/ritzgroup1122
B36: https://hindibookmark.com/ | C36: 89 | D36: 76 | E36: Profile Creation | F36: https://hindibookmark.com/user/ritzgroup1122
B37: https://claz.org/ | C37: 52 | D37: 55 | E37: Profile Creation | F37: https://claz.org/user/account
B38: https://www.quora.com/ | C38: 95 | D38: 86 | E38: Profile Creation | F38: https://www.quora.com/profile/Ritz-Group
B39: SBMS Submission
B40: https://www.submitcorp.com/ | C40: 28 | D40: 50 | E40: SBMS | F40: https://www.submitcorp.com/preview-business/ | G40: Pending
B41: https://www.peoplebookmarks.com/ | C41: 12 | D41: 41 | E41: SBMS | F41: https://www.peoplebookmarks.com/preview-bookmark/ | G41: Pending
B42: https://altbookmark.com/ | C42: 86 | D42: 52 | E42: SBMS | F42: https://altbookmark.com/story22701218/how-an-investors-club-can-boost-your-investment-knowledge-profits
B43: https://hindibookmark.com/ | C43: 97 | D43: 87 | E43: SBMS | F43: https://hindibookmark.com/story22786728/how-an-investors-club-can-boost-your-investment-knowledge-profits
B44: https://www.legacydirectory.com/ | C44: 34 | D44: 38 | E44: SBMS | F44: https://www.legacydirectory.com/preview-directory/ | G44: Pending
B45: Directory Submission
B46: https://www.firstlinkonline.info/ | C46: 65 | D46: 39 | E46: Directories | F46: https://www.firstlinkonline.info/submit.php?c=702&LINK_TYPE=8
B47: https://www.qualityinternetdirectory.com | C47: 20 | D47: 44 | E47: Directories | F47: https://www.qualityinternetdirectory.com/submit.php
B48: https://www.freeprwebdirectory.com | C48: 15 | D48: 50 | E48: Directories | F48: https://www.freeprwebdirectory.com/submit.php
B49: https://www.submissionwebdirectory.com | C49: 28 | D49: 28 | E49: Directories | F49: https://www.submissionwebdirectory.com/submit.php
B50: https://www.prolinkdirectory.com/ | C50: 34 | D50: 67 | E50: Directories | F50: https://www.prolinkdirectory.com/submit.php
B51: Classifieds
B52: https://indianapolis.claz.org/ | C52: 23 | D52: 43 | E52: Clasifieds | F52: https://indianapolis.claz.org/classifieds/services/finance/l272bbmn8a6xr-best-investment-company-in-india
B53: https://www.classifiedads.com | C53: 61 | D53: 35 | E53: Clasifieds | F53: https://www.classifiedads.com/financial_services/688z5knvb3dx9
B54: https://chennaiclassic.com/ | C54: 19 | D54: 48 | E54: Clasifieds | F54: https://chennaiclassic.com/listing/best-investment-company-in-india/
B55: https://www.yookalo.com | C55: 75 | D55: 86 | E55: Clasifieds | F55: https://www.yookalo.com/item-success
A56: 29/12/2025
B57: Profile submission
B58: www.pixlr.com | C58: 87 | D58: 66 | F58: https://pixlr.com/myaccount/
B59: https://manage.wix.com/ | C59: 44 | D59: 53 | F59: https://manage.wix.com/dashboard/c16d17bc-504a-4b82-9ad8-c0f581521d29/setup
B60: https://thejavasea.me/ | C60: 28 | D60: 40 | F60: https://thejavasea.me/members/ritzgroup.370953/
B61: https://participez.nouvelle-aquitaine.fr | C61: 61 | D61: 44 | F61: https://participez.nouvelle-aquitaine.fr/profiles/ritzgroup/timeline?locale=en
B62: https://www.tripit.com/ | C62: 78 | D62: 64 | F62: https://www.tripit.com/app/account/profile
B63: github.com | C63: 96 | D63: 93 | F63: https://github.com/ritzgroupco123-lgtm
B64: https://indiadial.in/ | C64: 34 | D64: 55 | F64: https://indiadial.in/my-profile.html
B65: https://www.articlealley.com/ | C65: 53 | D65: 52 | F65: https://www.articlealley.com/profile/ritzgroup
B66: https://indiafinder.in/ | C66: 14 | D66: 26 | F66: https://indiafinder.in/users/profile
B67: SBMS Submission
B68: https://www.bookmarkbuzz.com | C68: 15 | D68: 41 | F68: https://www.bookmarkbuzz.com/preview-bookmark
B69: https://www.directorynode.com | C69: 22 | D69: 41 | F69: https://directorynode.com/top-fund-management-services-in-india-features-benefits-how-to-choose-the-right-one/
B70: https://www.bookmarkinbox.info | C70: 14 | D70: 42 | F70: https://www.bookmarkinbox.info/preview-article/
B71: https://www.indusdirectory.com | C71: 17 | D71: 38 | F71: https://www.indusdirectory.com/preview-directory/
B72: directorysection.com | C72: 16 | D72: 42 | F72: https://www.socialbookmarkiseasy.info/preview-story/
B74: Directory Submission
B75: https://www.247webdirectory.com/ | C75: 24 | D75: 51 | F75: https://www.247webdirectory.com/?aspxerrorpath=/save.aspx
B76: https://www.ecobluedirectory.com/ | C76: 31 | D76: 45 | F76: https://www.ecobluedirectory.com/submit.php
B77: https://www.greenydirectory.com/ | C77: 22 | D77: 44 | F77: https://www.greenydirectory.com/submit.php
B78: https://www.reddit-directory.com/ | C78: 32 | D78: 46 | F78: https://www.reddit-directory.com/submit.php
B79: https://www.jayde.com/ | C79: 41 | D79: 56 | F79: https://www.jayde.com/landing.html
B81: Classifieds
B82: freeadsincanada.com | C82: 23 | D82: 43 | F82: http://andhra-pradesh.freeadsinindia.in/en-i-editResourceOffer-i-id-i-3212786-i-best-investment-company-in-india-ritzgroup.html
B83: https://www.canadianplanet.net | C83: 26 | D83: 50 | F83: https://www.canadianplanet.net/ritzgroup-investment-organization-F1108C1061BD54C
B84: https://www.classifiedsfactor.com/ | C84: 35 | D84: 56 | F84: https://items.classifiedsfactor.com/post-a-classified-ad-type.php
B85: https://www.topfreeclassifieds.com | C85: 14 | D85: 29 | F85: https://www.topfreeclassifieds.com/index.php?view=post&cityid=16&lang=en&catid=12&subcatid=82&shortcutregion=&
B86: https://indiadial.in | C86: 14 | D86: 26 | F86: https://indiadial.in/services/finance-legal/financial-advice/best-investment-company-in-india-291425.html
B88: Artical Submissions
B89: https://articlebiz.com/ | C89: 46 | D89: 53 | F89: https://articlebiz.com/checkArticle/statuses/ritzgroupco123%40gmail.com
B90: articlealley.com | C90: 53 | D90: 52 | F90: https://www.articlealley.com/list/best-investment-company-in-india-82825
B91: https://blog.freeadstime.org | C91: 37 | D91: 48 | F91: https://blogpost.freeadstime.org/post-an-article-steps.php
B93: Image Submissions
B94: https://www.smugmug.com/ | C94: 80 | D94: 64 | F94: https://www.smugmug.com/app/library/recent
B96: Pdf Submissions
B97: http://www.pinpdf.com/ | C97: 31 | D97: 37 | F97: https://pinpdf.com/best-investment-company-in-india-466f1065019d54dc0318ac914b162031.html
B98: www.slideshare.net | C98: 94 | D98: 86 | F98: https://www.slideshare.net/slideshow/ritz-group-greentech-fintech-healthtech-investments/284886954
B99: dochub.com | C99: 60 | D99: 58 | F99: https://www.docdroid.com/lEnO9Ck/off-page-pdf
B100: issuu.com | C100: 94 | D100: 83 | F100: https://issuu.com/ritzgroup/docs/best_investment_company_in_india
A101: 30/12/2025
B102: Profile submission
B103: https://www.beatstars.com/ | C103: 80 | D103: 60 | F103: https://www.beatstars.com/ritzgroupco123
B104: futurelab.my | C104: 35 | D104: 40 | F104: https://futurelab.my/mentee_profile/ritz-group
B105: https://tm-town.com/ | C105: 40 | D105: 46 | F105: https://tm-town.com///translators/ritzgroup
B106: https://www.jobcase.com | C106: 54 | D106: 52 | F106: https://www.jobcase.com/profile
...

Sheet web 2.0 backlinks
A1: Date | B1: URL | C1: Submission URL
A2: 23/12/2025 | B2: https://ko-fi.com | C2: https://ko-fi.com/i/IP5P51QBOMZ | D2: Gmail | E2: Password
B3: https://www.reddit.com/ | C3: https://www.reddit.com/r/investing_discussion/comments/1pn6oq7/best_investment_company_in_india_a_complete_guide/ | D3: ritzgroupco123@gmail.com | E3: Ritzgroup@1122
B4: https://justpaste.it | C4: https://justpaste.it/kh718
B5: https://www.blogger.com/ | C5: https://ritzgroupco1.blogspot.com/2025/12/best-investment-company-in-india.html
B6: https://medium.com | C6: https://medium.com/@ritzgroupco123/best-investment-company-in-india-a-complete-guide-to-smart-wealth-building-d2c4d8e33dc6?postPublishedType=initial
B7: https://www.tumblr.com | C7: https://www.tumblr.com/ritz1122/803002568796160000/best-investment-company-in-india-a-complete-guide?source=share
B8: https://pastes.io | C8: https://pastes.io/best-investment-company-in-india-a-complete-guide-to-smart-wealth-building
B9: https://www.diigo.com/ | C9: https://www.diigo.com/item/note/bpr5u/wsyx?k=9dc5059e0cf4df1b40f56717c0462ac2
B10: LiveJournal.com | C10: https://ext-6891250.livejournal.com/260.html
B11: https://blogs.hyvor.com/ | C11: https://ritz.hyvorblogs.io/best-investment-company-in-india-a-complete-guide-to-smart-wealth-building
B12: https://potswap.club | C12: https://potswap.club/posts/198705
B13: https://blogger-mania.mn.co/ | C13: https://blogger-mania.mn.co/posts/95068636?utm_source=manual
A15: 24/12/2025 | B15: https://justpaste.it | C15: https://justpaste.it/hj9y8
B16: https://www.blogger.com/ | C16: https://ritzgroupco1.blogspot.com/2025/12/how-to-choose-right-investment-company.html
B17: https://medium.com | C17: https://medium.com/@ritzgroupco123/how-to-choose-the-right-investment-company-for-long-term-wealth-growth-e60502903b4b?postPublishedType=initial
B18: https://www.tumblr.com | C18: https://www.tumblr.com/ritz1122/803789950252466176/how-to-choose-the-right-investment-company-for?source=share
B19: https://www.reddit.com/ | C19: https://www.reddit.com/r/investing/comments/1pufoft/how_to_choose_the_right_investment_company_for/
B20: LiveJournal.com | C20: https://ext-6891250.livejournal.com/1313.html
B21: https://www.diigo.com/ | C21: https://www.diigo.com/annotated/7ba0d26668e0f6d4cce3092596d47ba4
A23: 29/12/2025 | B23: https://justpaste.it | C23: https://justpaste.it/jrncm
B24: https://www.blogger.com/ | C24: https://ritzgroupco1.blogspot.com/2025/12/top-fund-management-services-in-india.html
B25: https://medium.com | C25: https://medium.com/@ritzgroupco123/top-fund-management-services-in-india-features-benefits-how-to-choose-the-right-one-5806fbd5c0df?postPublishedType=initial
B26: https://www.tumblr.com | C26: https://www.tumblr.com/ritz1122/804257130316201984/top-fund-management-services-in-india-features?source=share
B27: https://www.reddit.com/ | C27: https://www.reddit.com/r/investing/comments/1pyiw6b/top_fund_management_services_in_india_features/
B28: LiveJournal.com | C28: https://www.livejournal.com/post/?draft=https://ext-6891250.livejournal.com/d6.html
B29: https://www.diigo.com/ | C29: https://www.diigo.com/annotated/906f039359f87bd8bc12c1cc8338cb24
B30: https://ko-fi.com | C30: https://ko-fi.com/i/IP5P51QBOMZ
A32: 30/12/2025 | B32: https://justpaste.it | C32: https://justpaste.it/m7tf4
B33: https://www.blogger.com/ | C33: https://ritzgroupco1.blogspot.com/2025/12/ritz-group-greentech-fintech-healthtech.html
B34: https://medium.com | C34: https://medium.com/@ritzgroupco123/ritz-group-greentech-fintech-healthtech-investments-building-the-future-of-smart-capital-161ff9c181c7?postPublishedType=initial
B35: https://www.tumblr.com | C35: https://www.tumblr.com/ritz1122/804353592413782016/ritz-group-greentech-fintech-healthtech?source=share
B36: https://www.reddit.com/ | C36: https://www.reddit.com/r/investing_discussion/comments/1pzf2z8/ritz_group_greentech_fintech_healthtech/
B37: LiveJournal.com | C37: https://www.livejournal.com/post/?draft=https://ext-6891250.livejournal.com/d7.html
B38: https://www.diigo.com/ | C38: https://www.diigo.com/user/ritzgroup/b/813089518
A40: 31/12/2025 | B40: https://justpaste.it | C40: https://justpaste.it/e36fi
B41: https://www.blogger.com/ | C41: https://ritzgroupco1.blogspot.com/2025/12/micro-macro-investments-in-india.html
B42: https://medium.com | C42: https://medium.com/@ritzgroupco123/micro-macro-investments-in-india-a-complete-guide-for-smart-wealth-building-in-2025-972dc962a2bb?postPublishedType=initial
B43: https://www.tumblr.com | C43: https://www.tumblr.com/ritz1122/804445430537764864/micro-macro-investments-in-india-a-complete?source=share
B44: https://www.reddit.com/ | C44: https://www.reddit.com/r/Investments/comments/1q0aqkg/best_investment_company_in_india/
B45: https://in.pinterest.com/ | C45: https://in.pinterest.com/pin/999939923530558750/
B46: https://www.diigo.com/ | C46: https://www.diigo.com/item/image/bpr5u/c4jh?k=dcd7c2d8319c71ba2448994f73279a75
B47: https://www.smugmug.com/ | C47: https://www.smugmug.com/app/library/recent?imageKey=S8w3RQh
A49: 46054 | B49: https://justpaste.it/ | C49: https://justpaste.it/bt87x
B50: https://medium.com/ | C50: https://medium.com/@ritzgroupco123/top-venture-capital-firms-in-india-2025-the-ultimate-guide-for-startup-founders-63f4877aa529?postPublishedType=initial
B51: https://www.tumblr.com/ | C51: https://www.tumblr.com/ritz1122/804620386151153664/top-venture-capital-firms-in-india-2025-the?source=share
B52: https://ritzgroupco1.blogspot.com/ | C52: https://ritzgroupco1.blogspot.com/2026/01/top-venture-capital-firms-in-india-2025.html
B53: https://www.reddit.com/ | C53: https://www.reddit.com/r/Investments/comments/1q1ue91/top_venture_capital_firms_in_india_2025_the/
B54: https://www.diigo.com/ | C54: https://www.diigo.com/annotated/da383262c2624780e6244106813844e6
B55: https://in.pinterest.com/ | C55: https://in.pinterest.com/pin/999939923530642833/
B56: https://postimg.cc/ | C56: https://postimg.cc/vxfn9KH6
A58: 46143 | B58: https://justpaste.it/ | C58: https://justpaste.it/l2rgo
B59: https://medium.com/ | C59: https://medium.com/@ritzgroupco123/business-investors-in-india-why-joining-investors-clubs-is-the-smartest-move-in-2026-5cec48af95b5?postPublishedType=initial
B60: https://www.tumblr.com/ | C60: https://www.tumblr.com/ritz1122/804902104211800064/business-investors-in-india-why-joining?source=share
B61: https://ritzgroupco1.blogspot.com/ | C61: https://ritzgroupco1.blogspot.com/2026/01/business-investors-in-india-why-joining.html
B62: https://www.reddit.com/ | C62: https://www.reddit.com/r/Investments/comments/1q4k5o2/best_investment_company_in_india/
B63: https://www.diigo.com/ | C63: https://www.diigo.com/user/ritzgroup/b/814146277
B64: LiveJournal.com | C64: https://www.livejournal.com/post/?draft=https://ext-6891250.livejournal.com/d9.html
B65: https://www.quora.com/ | C65: https://www.quora.com/profile/Ritz-Group/Choose-an-investment-journey-that-matches-your-goals-Silver-Gold-or-Diamond-invest-with-confidence-at-every-stage-St
B66: https://ko-fi.com/ritzgroup/ | C66: https://ko-fi.com/ritzgroup/gallery#galleryItemView
A68: 46174 | B68: https://justpaste.it/ | C68: https://justpaste.it/9900d
B69: https://medium.com/ | C69: https://medium.com/@ritzgroupco123/smart-investment-strategies-for-building-long-term-wealth-in-2026-0054891ef93d?postPublishedType=initial
B70: https://www.tumblr.com/ | C70: https://www.tumblr.com/ritz1122/804987649517584384/smart-investment-strategies-for-building-long-term?source=share
B71: https://ritzgroupco1.blogspot.com/ | C71: https://ritzgroupco1.blogspot.com/2026/01/smart-investment-strategies-for.html
B72: https://www.reddit.com/ | C72: https://www.reddit.com/r/Investors/comments/1q5g6fr/smart_investment_strategies_for_building_longterm/
B73: https://www.diigo.com/ | C73: https://www.diigo.com/annotated/7ba0d26668e0f6d4cce3092596d47ba4
B74: https://ko-fi.com/ | C74: https://ko-fi.com/ritzgroup#galleryItemView
A76: 46204 | B76: https://justpaste.it/ | C76: https://justpaste.it/e16pj
B77: https://medium.com/ | C77: https://medium.com/@ritzgroupco123/top-venture-capital-firms-in-india-2025-how-to-choose-the-right-vc-for-your-startup-f107cb9c2e0d?postPublishedType=initial
B78: https://www.tumblr.com/ | C78: https://www.tumblr.com/ritz1122/805086166657449984/top-venture-capital-firms-in-india-2025-how-to?source=share
B79: https://ritzgroupco1.blogspot.com/ | C79: https://ritzgroupco1.blogspot.com/2026/01/top-venture-capital-firms-in-india-2025_7.html
B80: https://www.reddit.com/ | C80: https://www.reddit.com/r/Investments/comments/1q6eo58/fund_management_services_in_india/
B81: https://www.diigo.com/ | C81: https://www.diigo.com/item/image/bpr5u/nocs?k=dac5ac9a562f71e4086d88b9806cbf78
A83: 46235 | B83: https://justpaste.it/ | C83: https://justpaste.it/hpsk1
B84: https://medium.com/ | C84: https://medium.com/@ritzgroupco123/best-investment-company-in-india-how-to-choose-the-right-partner-for-your-financial-growth-aed285d11bac?postPublishedType=initial
B85: https://www.tumblr.com/ | C85: https://www.tumblr.com/ritz1122/805169832574287872/best-investment-company-in-india-how-to-choose?source=share
B86: https://ritzgroupco1.blogspot.com/ | C86: https://ritzgroupco1.blogspot.com/2026/01/best-investment-company-in-india-how-to.html
B87: https://www.reddit.com/ | C87: https://www.reddit.com/r/Investors/comments/1q78z9k/best_investment_company_in_india_how_to_choose/
B88: https://www.diigo.com/ | C88: https://www.diigo.com/user/ritzgroup/b/814796855
B89: https://ko-fi.com/ | C89: https://ko-fi.com/ritzgroup/gallery#galleryItemView
B90: https://in.pinterest.com/ | C90: https://in.pinterest.com/pin/999939923530909159
A92: 46357 | B92: https://justpaste.it/ | C92: https://justpaste.it/l0923
B93: https://medium.com/ | C93: https://medium.com/@ritzgroupco123/top-fund-management-services-in-india-how-to-grow-your-wealth-smartly-in-2026-d23259b9d776?postPublishedType=initial
B94: https://www.tumblr.com/ | C94: https://www.tumblr.com/ritz1122/805529139845136384/top-fund-management-services-in-india-how-to-grow?source=share
B95: https://ritzgroupco1.blogspot.com/ | C95: https://ritzgroupco1.blogspot.com/2026/01/top-fund-management-services-in-india.html
B96: https://www.reddit.com/ | C96: https://www.reddit.com/r/investing/comments/1qark6y/best_investment_company_in_india_how_to_choose/
B97: https://www.diigo.com/ | C97: https://www.diigo.com/item/image/bpr5u/h8u0?k=b75beb099202ba27b02af89176fb44ce
B98: https://ko-fi.com/ | C98: https://ko-fi.com/ritzgroup#galleryItemView
B99: https://in.pinterest.com/ | C99: https://in.pinterest.com/pin/999939923531090749/
B100: https://esolz.hashnode.dev/ | C100: https://best-investment-company-in-india.hashnode.dev/top-fund-management-services-in-india-how-to-grow-your-wealth-smartly-in-2026?showSharer=true
A102: 13/1/2026 | B102: https://justpaste.it/ | C102: https://justpaste.it/lbfix
B103: https://medium.com/ | C103: https://medium.com/@ritzgroupco123/beginners-guide-to-investment-where-to-start-and-how-to-grow-your-money-f20e279bcc1d?postPublishedType=initial
B104: https://www.tumblr.com/ | C104: https://www.tumblr.com/ritz1122/805621093294587904/beginners-guide-to-investment-where-to-start-and?source=share
B105: https://ritzgroupco1.blogspot.com/ | C105: https://ritzgroupco1.blogspot.com/2026/01/beginners-guide-to-investment-where-to.html
B106: https://www.reddit.com/ | C106: https://www.reddit.com/r/investimentoslivre/comments/1qbo3oi/grow_your_wealth_with_smart_savings_investment/
B107: https://www.diigo.com/ | C107: https://www.diigo.com/annotated/7ba0d26668e0f6d4cce3092596d47ba4
B108: https://ko-fi.com/ | C108: https://ko-fi.com/ritzgroup/posts
B109: https://esolz.hashnode.dev/ | C109: https://best-investment-company-in-india.hashnode.dev/beginners-guide-to-investment-where-to-start-and-how-to-grow-your-money?showSharer=true
A111: 14/1/2026 | B111: https://justpaste.it/ | C111: https://justpaste.it/eykin
B112: https://medium.com/ | C112: https://medium.com/@ritzgroupco123/best-investment-company-in-hyderabad-how-to-choose-the-right-partner-for-your-financial-growth-13335cd0243b?postPublishedType=initial
...

Sheet Profile Creations
A1: Referring URl | B1: DA | C1: PA | D1: Type of Submission | E1: Submitted URl | F1: Status
A2: https://www.ranker.com/ | B2: 95 | C2: 85 | D2: Profile Creation | E2: https://www.ranker.com/writer/ritz-group | G2: Gmail | H2: Password
A3: https://devfolio.co/ | B3: 76 | C3: 64 | D3: Profile Creation | E3: https://devfolio.co/@Ritzgroup | G3: ritzgroupco123@gmail.com | H3: Ritzgroup@1122
A4: https://www.atlasobscura.com/ | B4: 83 | C4: 68 | D4: Profile Creation | E4: https://www.atlasobscura.com/users/9f4f3c46-ee34-4a9b-bd72-61cffd6b8ab8
A5: https://www.answers.com/ | B5: 15 | C5: 24 | D5: Profile Creation | E5: https://www.answers.com/u/ritzgroup
A6: https://www.indiegogo.com/ | B6: 90 | C6: 70 | D6: Profile Creation | E6: https://www.indiegogo.com/en/profile/ritz12345#/overview
A7: https://bookmarkrange.com/ | B7: 54 | C7: 45 | D7: Profile Creation | E7: https://bookmarkrange.com/user/ritzgroup1122
A8: https://www.pinterest.com/ | B8: 35 | C8: 56 | D8: Profile Creation | E8: https://www.pinterest.com/ritzgroupco123/
A9: 24/12/2025
A10: https://justpaste.it/ | B10: 76 | C10: 64 | D10: Profile Creation | E10: https://justpaste.it/u/Ritzgroup1122
A11: https://medium.com/ | B11: 83 | C11: 68 | D11: Profile Creation | E11: https://medium.com/@ritzgroupco123
A12: https://dev.to/ | B12: 83 | C12: 68 | D12: Profile Creation | E12: https://dev.to/ritz_group_00b92b8a0f04df
A13: https://www.spreaker.com | B13: 90 | C13: 70 | D13: Profile Creation | E13: https://www.spreaker.com/user/ritz-group--18836066
A14: www.gitlab.com | B14: 92 | C14: 66 | D14: Profile Creation | E14: https://gitlab.com/ritzgroupco123
A15: https://altbookmark.com/ | B15: 15 | C15: 37 | D15: Profile Creation | E15: https://altbookmark.com/user/ritzgroup1122
A16: https://hindibookmark.com/ | B16: 89 | C16: 76 | D16: Profile Creation | E16: https://hindibookmark.com/user/ritzgroup1122
A17: https://claz.org/ | B17: 52 | C17: 55 | D17: Profile Creation | E17: https://claz.org/user/account
A18: https://www.quora.com/ | B18: 95 | C18: 86 | D18: Profile Creation | E18: https://www.quora.com/profile/Ritz-Group
A19: 29/12/2025
A20: www.pixlr.com | B20: 87 | C20: 66 | D20: Profile Creation | E20: https://pixlr.com/myaccount/
A21: https://manage.wix.com/ | B21: 44 | C21: 53 | D21: Profile Creation | E21: https://manage.wix.com/dashboard/c16d17bc-504a-4b82-9ad8-c0f581521d29/setup
A22: https://thejavasea.me/ | B22: 28 | C22: 40 | D22: Profile Creation | E22: https://thejavasea.me/members/ritzgroup.370953/
A23: https://participez.nouvelle-aquitaine.fr | B23: 61 | C23: 44 | D23: Profile Creation | E23: https://participez.nouvelle-aquitaine.fr/profiles/ritzgroup/timeline?locale=en
A24: https://www.tripit.com/ | B24: 78 | C24: 64 | D24: Profile Creation | E24: https://www.tripit.com/app/account/profile
A25: github.com | B25: 96 | C25: 93 | D25: Profile Creation | E25: https://github.com/ritzgroupco123-lgtm
A26: https://indiadial.in/ | B26: 34 | C26: 55 | D26: Profile Creation | E26: https://indiadial.in/my-profile.html
A27: https://www.articlealley.com/ | B27: 53 | C27: 52 | D27: Profile Creation | E27: https://www.articlealley.com/profile/ritzgroup
A28: https://indiafinder.in/ | B28: 14 | C28: 26 | D28: Profile Creation | E28: https://indiafinder.in/users/profile
A29: 30/12/2025
A30: https://www.beatstars.com/ | B30: 80 | C30: 60 | D30: Profile Creation | E30: https://www.beatstars.com/ritzgroupco123
A31: futurelab.my | B31: 35 | C31: 40 | D31: Profile Creation | E31: https://futurelab.my/mentee_profile/ritz-group
A32: https://tm-town.com/ | B32: 40 | C32: 46 | D32: Profile Creation | E32: https://tm-town.com///translators/ritzgroup
A33: https://www.jobcase.com | B33: 54 | C33: 52 | D33: Profile Creation | E33: https://www.jobcase.com/profile
A34: https://www.longisland.com | B34: 81 | C34: 59 | D34: Profile Creation | E34: https://www.longisland.com/accounts/overview/
A35: https://dash.e.jimdo.com/ | B35: 43 | C35: 54 | D35: Profile Creation | E35: https://dash.e.jimdo.com/profile
A36: https://www.mikroe.com/ | B36: 59 | C36: 51 | D36: Profile Creation | E36: https://www.mikroe.com/my-account
A37: https://www.stocksy.com/ | B37: 69 | C37: 56 | D37: Profile Creation | E37: https://www.stocksy.com/user/edit-profile
A38: https://www.alamy.com | B38: 91 | C38: 66 | D38: Profile Creation | E38: https://www.alamy.com/myalamycustomer.aspx
A39: https://www.ning.com/ | B39: 59 | C39: 51 | D39: Profile Creation | E39: https://www.ning.com/account
A40: https://businessdirectoryphil.com/ | B40: 34 | C40: 57 | D40: Profile Creation | E40: https://businessdirectoryphil.com/wp-admin/profile.php
A41: https://www.easypolls.net/ | B41: 23 | C41: 44 | D41: Profile Creation | E41: https://www.easypolls.net/#/account
A42: https://www.ukclassifieds.co.uk | B42: 39 | C42: 51 | D42: Profile Creation | E42: https://www.ukclassifieds.co.uk/user/profile/111911
A43: 31/12/2025
A44: https://www.ted.com/ | B44: 41 | C44: 27 | D44: Profile Creation | E44: https://www.ted.com/profiles/50885393
A45: https://www.behance.net/ | B45: 70 | C45: 57 | D45: Profile Creation | E45: https://www.behance.net/ritzgroup
A46: https://www.sbnation.com/ | B46: 35 | C46: 43 | D46: Profile Creation | E46: https://www.sbnation.com/account/profile
A47: https://betterphoto.com | B47: 18 | C47: 40 | D47: Profile Creation | E47: https://betterphoto.com/my-account/your-profile/
A48: https://vimeo.com/ | B48: 78 | C48: 63 | D48: Profile Creation | E48: https://vimeo.com/user252528454
A49: https://www.zillow.com/ | B49: 92 | C49: 79 | D49: Profile Creation | E49: https://www.zillow.com/myzillow/account/
A50: https://bloggazzo.com/ | B50: 84 | C50: 55 | D50: Profile Creation | E50: https://bloggazzo.com/users
A51: https://www.ibm.com | B51: 87 | C51: 66 | D51: Profile Creation | E51: https://www.ibm.com/ibmweb/myibm/us-en/profile
A52: https://www.redbubble.com/ | B52: 84 | C52: 55 | D52: Profile Creation | E52: https://www.redbubble.com/people/Ritzgroup/shop?asc=u
A53: https://mix.com/ | B53: 90 | C53: 77 | D53: Profile Creation | E53: https://mix.com/ritzgroup
A54: https://www.a1articles.com | B54: 18 | C54: 40 | D54: Profile Creation | E54: https://www.a1articles.com/profile/ritzgroup
A55: https://e27.co/ | B55: 50 | C55: 58 | D55: Profile Creation | E55: https://e27.co/user/ritz.group/
... A62: https://www.deviantart.com/ | B62: 64 | C62: 34 | D62: Profile Creation | E62: https://www.deviantart.com/ritz1122
A63: 46054
A64: https://soundcloud.com | B64: 88 | C64: 76 | D64: Profile Creation | E64: https://soundcloud.com/ritz-group
A65: https://sourceforge.net/ | B65: 15 | C65: 23 | D65: Profile Creation | E65: https://sourceforge.net/u/ritzgroup/profile
A66: https://www.change.org/ | B66: 62 | C66: 58 | D66: Profile Creation | E66: https://www.change.org/u/me?source_location=my_petitions_dropdown
A67: https://forum.parallels.com/ | B67: 29 | C67: 50 | D67: Profile Creation | E67: https://forum.parallels.com/account/
A68: https://themeforest.net/ | B68: 25 | C68: 30 | D68: Profile Creation | E68: https://themeforest.net/user/ritzgroupco123
A69: https://limewire.com/ | B69: 44 | C69: 56 | D69: Profile Creation | E69: https://limewire.com/u/profile
A70: https://about.me/ | B70: 88 | C70: 59 | D70: Profile Creation | E70: https://about.me/ritzgroup
A71: 46143
A72: zintro.com | B72: 57 | C72: 54 | D72: Profile Creation | E72: https://app.zintro.com/profile/zi79b38794?ref=
A73: https://openlibrary.org | B73: 74 | C73: 71 | D73: Profile Creation | E73: https://openlibrary.org/people/ritz_group
A74: https://parler.com | B74: 64 | C74: 60 | D74: Profile Creation | E74: https://app.parler.com/ritzgroupco
A75: https://in.radiocut.fm/ | B75: 67 | C75: 43 | D75: Profile Creation | E75: https://in.radiocut.fm/user/group.ritz/
A76: https://www.elephantjournal.com/ | B76: 79 | C76: 59 | D76: Profile Creation | E76: https://www.elephantjournal.com/profile/ritzgroupco123/
A77: pinshape.com | B77: 72 | C77: 65 | D77: Profile Creation | E77: https://pinshape.com/users/8879125-ritzgroupco123?tab=designs
A78: https://www.webclassifieds.us/ | B78: 65 | C78: 84 | D78: Profile Creation | E78: https://www.webclassifieds.us/forum/members/ritzgroupco12.109372/
A79: https://myphoto.eu/ | B79: 43 | C79: 54 | D79: Profile Creation | E79: https://myphoto.eu/ritzgroupco123/profile/
A80: https://app.parler.com/ | B80: 33 | C80: 64 | D80: Profile Creation | E80: https://app.parler.com/ritzgroupco
A81: 46174
A82: https://devpost.com | B82: 84 | C82: 63 | D82: Profile Creation | E82: https://devpost.com/ritzgroupco123?ref_content=user-portfolio&ref_feature=portfolio&ref_medium=global-nav
A83: https://www.easel.ly | B83: 66 | C83: 61 | D83: Profile Creation | E83: https://www.easel.ly/dashboard#
A84: https://www.feedsfloor.com | B84: 89 | C84: 68 | D84: Profile Creation | E84: https://www.feedsfloor.com/profile/ritz-group
A85: https://seekingalpha.com/ | B85: 94 | C85: 86 | D85: Profile Creation | E85: https://seekingalpha.com/user/63926977
A86: https://www.idealist.org/ | B86: 52 | C86: 55 | D86: Profile Creation | E86: https://www.idealist.org/dashboard/account-settings
A87: https://www.productmafia.com/ | B87: 94 | C87: 83 | D87: Profile Creation | E87: https://www.productmafia.com/membership/
A88: https://www.elzse.com/ | B88: 33 | C88: 54 | D88: Profile Creation | E88: https://www.elzse.com/user/profile
A89: https://www.imagevenue.com/ | B89: 55 | C89: 48 | D89: Profile Creation | E89: https://www.imagevenue.com/my/account
A90: 46204
A91: https://hub.docker.com/ | B91: 54 | C91: 53 | D91: Profile Creation | E91: https://hub.docker.com/u/ritzgroup1122
A92: https://recordsetter.com// | B92: 70 | C92: 49 | D92: Profile Creation | E92: https://recordsetter.com//user/ritzgroup
A93: https://reactos.org/ | B93: 92 | C93: 65 | D93: Profile Creation | E93: https://reactos.org/roslogin/?p=selfservice
A94: https://www.credly.com/ | B94: 91 | C94: 59 | D94: Profile Creation | E94: https://www.credly.com/users/ritz-group/edit#credly
A95: https://karmav.com | B95: 87 | C95: 71 | D95: Profile Creation | E95: https://karmav.com/user/profile
A96: https://giphy.com/channel/ | B96: 34 | C96: 65 | D96: Profile Creation | E96: https://giphy.com/channel/ritzgroup
A97: 46235
A98: https://www.mikroe.com/ | B98: 35 | C98: 40 | D98: Profile Creation | E98: https://www.mikroe.com/my-account
A99: https://foter.com/ | B99: 40 | C99: 46 | D99: Profile Creation | E99: https://foter.com/profile/
A100: https://www.coursera.org/ | B100: 61 | C100: 44 | D100: Profile Creation | E100: https://www.coursera.org/account-profile
A101: https://portal.ckeditor.com/ | B101: 54 | C101: 52 | D101: Profile Creation | E101: https://portal.ckeditor.com/settings
A102: https://www.oregonlive.com/ | B102: 59 | C102: 51 | D102: Profile Creation | E102: https://www.oregonlive.com/account/
A103: https://www.99bookmarking.com/ | B103: 81 | C103: 59 | D103: Profile Creation | E103: https://www.99bookmarking.com/profile
A104: https://bookmarkingpage.com/ | B104: 45 | C104: 34 | D104: Profile Creation | E104: https://bookmarkingpage.com/user.php?login=Ritzgroup
A105: https://www.anibookmark.com/ | B105: 66 | C105: 74 | D105: Profile Creation | E105: https://www.anibookmark.com/user/ritzgroup.html
A106: 46266
...

Sheet Social Bookmarks
A1: Referring URl | B1: DA | C1: PA | D1: Type of Submission | E1: Submitted URl | F1: Status
A2: https://bookmarkrange.com/ | B2: 11 | C2: 42 | D2: SBMS | E2: https://bookmarkrange.com/story22617237/how-to-choose-the-right-investment-company-for-long-term-wealth-growth
A3: https://bookmarkbirth.com/ | B3: 15 | C3: 40 | D3: SBMS | E3: https://bookmarkbirth.com/story21340511/how-to-choose-the-right-investment-company-for-long-term-wealth-growth | G3: Gmail | H3: Password
A4: https://www.bookmarkfeeds.com | B4: 55 | C4: 64 | D4: SBMS | E4: https://www.bookmarkfeeds.com/how-to-choose-the-right-investment-company-for-long-term-wealth-growth/ | G4: ritzgroupco123@gmail.com | H4: Ritzgroup@1122
A5: https://www.socialbookmarknow.info/ | B5: 18 | C5: 41 | D5: SBMS | E5: https://www.socialbookmarknow.info/how-to-choose-the-right-investment-company-for-long-term-wealth-growth/
A6: https://www.publicbuysell.com/ | B6: 42 | C6: 55 | D6: SBMS | E6: https://www.publicbuysell.com/how-to-choose-the-right-investment-company-for-long-term-wealth-growth/
A7: 24/12/2025
A8: https://www.submitcorp.com/ | B8: 28 | C8: 50 | D8: SBMS | E8: https://www.submitcorp.com/how-an-investors-club-can-boost-your-investment-knowledge-profits/
A9: https://www.peoplebookmarks.com/ | B9: 12 | C9: 41 | D9: SBMS | E9: https://www.peoplebookmarks.com/how-an-investors-club-can-boost-your-investment-knowledge-profits/
A10: https://altbookmark.com/ | B10: 86 | C10: 52 | D10: SBMS | E10: https://altbookmark.com/story22701218/how-an-investors-club-can-boost-your-investment-knowledge-profits
A11: https://hindibookmark.com/ | B11: 97 | C11: 87 | D11: SBMS | E11: https://hindibookmark.com/story22786728/how-an-investors-club-can-boost-your-investment-knowledge-profits
A12: https://www.legacydirectory.com/ | B12: 34 | C12: 38 | D12: SBMS | E12: https://www.legacydirectory.com/how-an-investors-club-can-boost-your-investment-knowledge-profits/
A13: 29/12/2025
A14: https://www.bookmarkbuzz.com | B14: 15 | C14: 41 | E14: https://www.bookmarkbuzz.com/top-fund-management-services-in-india-features-benefits-how-to-choose-the-right-one/
A15: https://www.directorynode.com | B15: 22 | C15: 41 | E15: https://directorynode.com/top-fund-management-services-in-india-features-benefits-how-to-choose-the-right-one/
A16: https://www.bookmarkinbox.info | B16: 14 | C16: 42 | E16: https://www.bookmarkinbox.info/top-fund-management-services-in-india-features-benefits-how-to-choose-the-right-one/
A17: https://www.indusdirectory.com | B17: 17 | C17: 38 | E17: https://www.indusdirectory.com/top-fund-management-services-in-india-features-benefits-how-to-choose-the-right-one/
A18: directorysection.com | B18: 16 | C18: 42 | E18: https://www.socialbookmarkiseasy.info/micro-macro-investments-in-india-a-complete-guide-for-smart-wealth-building-in-2025/
A19: 30/12/2025
A20: https://bouchesocial.com | B20: 75 | C20: 55 | E20: https://bouchesocial.com/story23065424/ritz-group-greentech-fintech-healthtech-investments-building-the-future-of-smart-capital
A21: https://socialmarkz.com | B21: 45 | C21: 34 | E21: https://socialmarkz.com/story11425277/how-to-choose-the-right-investment-company-for-long-term-wealth-growth
A22: https://bookmarketmaven.com | B22: 66 | C22: 75 | E22: https://bookmarketmaven.com/story21659913/how-an-investors-club-can-boost-your-investment-knowledge-profits
A23: https://socialmphl.com/ | B23: 55 | C23: 46 | E23: https://socialmphl.com/story23061197/top-fund-management-services-in-india-features-benefits-how-to-choose-the-right-one
A24: https://socialmediainuk.com/ | B24: 26 | C24: 46 | E24: https://socialmediainuk.com/story25218660/ritz-group-greentech-fintech-healthtech-investments-building-the-future-of-smart-capital
A25: https://start.me/ | B25: 19 | C25: 41 | E25: https://start.me/p/YQjDqJ/ritz-group-greentech-fintech-healthtech-inves
A26: https://www.social-bookmarkingsites.com/ | B26: 31 | C26: 40 | E26: https://www.social-bookmarkingsites.com/story/ritz-group-greentech-fintech-healthtech-investments-building-the-future-of-smart-capital-2
A27: https://www.sbookmarking.com/ | B27: 18 | C27: 41 | E27: https://www.sbookmarking.com/profile
A28: 31/12/2025
A29: https://www.submitportal.com/ | B29: 14 | C29: 41 | E29: https://www.submitportal.com/micro-macro-investments-in-india-a-complete-guide-for-smart-wealth-building-in-2025/
A30: https://www.activebookmarks.com | B30: 30 | C30: 50 | E30: https://www.activebookmarks.com/preview-bookmark/
A31: https://www.bsocialbookmarking.info | B31: 23 | C31: 45 | E31: https://www.bsocialbookmarking.info/top-fund-management-services-in-india-features-benefits-how-to-choose-the-right-one/
A32: https://www.votetags.com | B32: 27 | C32: 49 | E32: https://www.votetags.com/how-an-investors-club-can-boost-your-investment-knowledge-profits/
A33: https://www.onlinewebmarks.com | B33: 28 | C33: 50 | E33: https://www.onlinewebmarks.com/how-to-choose-the-right-investment-company-for-long-term-wealth-growth/
A34: https://www.bookmarktheme.com | B34: 22 | C34: 44 | E34: https://www.bookmarktheme.com/best-investment-company-in-india/
A35: 46054
A36: https://bookmark-share.com/ | B36: 28 | C36: 40 | E36: https://bookmark-share.com/story20924506/top-venture-capital-firms-in-india-2025-the-ultimate-guide-for-startup-founders
A37: https://hypebookmarking.com/ | B37: 38 | C37: 43 | E37: https://hypebookmarking.com/story20651953/best-investment-company-in-india
A38: https://www.richbookmarks.com | B38: 74 | C38: 68 | E38: https://www.richbookmarks.com/fund-management-services-in-india/
A39: https://www.bookmarkwiki.com/ | B39: 50 | C39: 50 | E39: https://www.bookmarkwiki.com/ritz-group-%e2%80%93-greentech-fintech-healthtech-investments-building-the-future-of-smart-capital/
A40: https://www.premiumbookmarks.com/ | B40: 35 | C40: 43 | E40: https://www.premiumbookmarks.com/how-to-choose-the-right-investment-company-for-long-term-wealth-growth/
A41: 46143
A42: https://www.serviceplaces.com/ | B42: 10 | C42: 41 | E42: https://www.serviceplaces.com/business-investors-in-india-why-joining-investors-clubs-is-the-smartest-move-in-2026/
A43: www.ukbookmarks.com | B43: 16 | C43: 38 | E43: https://www.ukbookmarks.com/business-investors-in-india-why-joining-investors-clubs-is-the-smartest-move-in-2026/
A44: https://samaysawara.in/ | B44: 27 | C44: 44 | E44: https://samaysawara.in/story/best-investment-company-in-india-ritz-group
A45: https://www.corpbookmarks.com/ | B45: 11 | C45: 40 | E45: https://www.corplistings.com/business-investors-in-india-why-joining-investors-clubs-is-the-smartest-move-in-2026/
A46: www.newsciti.com | B46: 28 | C46: 49 | E46: https://www.newsciti.com/top-venture-capital-firms-in-india-2025-the-ultimate-guide-for-startup-founders/
A47: www.businessveyor.com | B47: 12 | C47: 40 | E47: https://www.businessveyor.com/top-fund-management-services-in-india-features-benefits-how-to-choose-the-right-one/
A48: 46174
A49: https://www.bookmarkfollow.com/ | B49: 50 | C49: 50 | E49: https://www.bookmarkfollow.com/preview-listing/
A50: https://www.openfaves.com/ | B50: 35 | C50: 43 | E50: https://www.openfaves.com/preview-article/
A51: https://www.businessorgs.com/ | B51: 50 | C51: 51 | E51: https://www.businessorgs.com/preview-listing/
A52: https://www.free-socialbookmarking.com | B52: 63 | C52: 55 | E52: https://www.free-socialbookmarking.com/story/smart-investment-strategies-for-building-long-term-wealth-in-2026
A53: https://www.bookmarkingfree.com/ | B53: 60 | C53: 53 | E53: https://www.bookmarkingfree.com/story/top-venture-capital-firms-in-india-2025-the-ultimate-guide-for-startup-founders
A54: https://www.newsocialbookmarkingsite.com/ | B54: 90 | C54: 76 | E54: https://www.newsocialbookmarkingsite.com/story/how-an-investors-club-can-boost-your-investment-knowledge-profits
A55: 46204
A56: https://www.abookmarking.com/ | B56: 82 | C56: 69 | E56: https://www.abookmarking.com/story/top-venture-capital-firms-in-india-2025-how-to-choose-the-right-vc-for-your-startup
A57: https://bookmarkstime.com/ | B57: 25 | C57: 42 | E57: https://bookmarkstime.com/story21538997/top-venture-capital-firms-in-india-2025-how-to-choose-the-right-vc-for-your-startup
A58: https://gatherbookmarks.com/ | B58: 58 | C58: 64 | E58: https://gatherbookmarks.com/story21804976/how-an-investors-club-can-boost-your-investment-knowledge-profits
A59: https://bookmarkspring.com/ | B59: 48 | C59: 50 | E59: https://bookmarkspring.com/story16018642/top-fund-management-services-in-india-features-benefits-how-to-choose-the-right-one
A60: https://bookmarkextent.com/ | B60: 44 | C60: 67 | E60: https://bookmarkextent.com/story22933141/micro-macro-investments-in-india-a-complete-guide-for-smart-wealth-building-in-2025
A61: 46235
A62: https://bookmarkingpage.com/ | B62: 81 | C62: 59 | E62: https://bookmarkingpage.com/new.php
A63: https://bookmark-template.com/ | B63: 69 | C63: 56 | E63: https://bookmark-template.com/story27179270/how-an-investors-club-can-boost-your-investment-knowledge-profits
A64: https://www.anibookmark.com/ | B64: 91 | C64: 66 | E64: https://www.anibookmark.com/site/top-fund-management-services-in-india-features-benefits-and-how-to-choose-the-right-one-ab2240023.html
A65: https://www.bookmarkgroups.com/ | B65: 93 | C65: 78 | E65: https://www.bookmarkgroups.com/ritz-group-%e2%80%93-greentech-fintech-healthtech-investments-building-the-future-of-smart-capital/
A66: https://www.socialbookmarkiseasy.info/ | B66: 59 | C66: 51 | E66: https://www.socialbookmarkiseasy.info/micro-macro-investments-in-india-a-complete-guide-for-smart-wealth-building-in-2025/
A67: https://www.bookmarkcart.info/ | B67: 39 | C67: 51 | E67: https://www.bookmarkcart.info/top-venture-capital-firms-in-india-2025-the-ultimate-guide-for-startup-founders/
A68: https://www.a1bookmarks.com | B68: 43 | C68: 59 | E68: https://www.a1bookmarks.com/business-investors-in-india-why-joining-investors-clubs-is-the-smartest-move-in-2026/
A69: 46266
A70: https://www.letsdobookmark.com/ | B70: 81 | C70: 59 | E70: https://www.letsdobookmark.com/story/best-investment-company-in-hyderabad
A71: https://www.pbookmarking.com/ | B71: 80 | C71: 50 | E71: https://www.pbookmarking.com/story/top-venture-capital-firms-in-hyderabad
A72: https://www.ubookmarking.com/ | B72: 43 | C72: 54 | E72: https://www.ubookmarking.com/story/fund-management-services-in-h
A73: https://www.ybookmarking.com/ | B73: 59 | C73: 51 | E73: https://www.ybookmarking.com/story/top-venture-capital-firms-in-hyderabad
A74: https://fastbookmarkings.com/ | B74: 81 | C74: 59 | E74: https://fastbookmarkings.com/story/business-investors-in-hyderabad-investors-clubs
A75: https://www.realbookmarking.com/ | B75: 65 | C75: 73 | E75: https://www.realbookmarking.com/story/business-investors-in-india-investors-clubs
A76: 46357
A77: https://www.starbookmarking.com/ | B77: 74 | C77: 68 | E77: https://www.starbookmarking.com/story/top-fund-management-services-in-india-how-to-grow-your-wealth-smartly-in-2026
A78: https://www.freebookmarkingsite.com/ | B78: 50 | C78: 50 | E78: https://www.freebookmarkingsite.com/story/top-fund-management-services-in-india-how-to-grow-your-wealth-smartly-in-2026
A79: https://www.social-bookmarkingsites.com/ | B79: 35 | C79: 43 | E79: https://www.social-bookmarkingsites.com/story/business-investors-in-india-why-joining-investors-clubs-is-the-smartest-move-in-2026
A80: https://www.sbookmarking.com/ | B80: 50 | C80: 51 | E80: https://www.sbookmarking.com/story/top-venture-capital-firms-in-hyderabad-how-to-ch
A81: https://ritzgroup.livepositively.com/ | B81: 63 | C81: 55 | E81: https://ritzgroup.livepositively.com/top-fund-management-services-in-india-how-to-grow-your-wealth-smartly-in-2026
A82: 13/01/2026
A83: https://www.mbookmarking.com/ | B83: 19 | C83: 40 | E83: https://www.mbookmarking.com/story/best-investment-company-in-hyderabad
A84: https://www.seolinksubmit.com/ | B84: 20 | C84: 42 | E84: https://www.seolinksubmit.com/business-investors-in-hyderabad-investors-clubs/
A85: https://www.businessfollow.com/ | B85: 46 | C85: 49 | E85: https://www.businessfollow.com/fund-management-services-in-hyderabad/
A86: https://addbusinessnow.com/ | B86: 48 | C86: 49 | E86: https://addbusinessnow.com/top-venture-capital-firms-in-hyderabad/
A87: https://www.bookmarkinghost.info/ | B87: 14 | C87: 39 | E87: https://www.bookmarkinghost.info/micro-macro-investments-in-hyderabad/
A88: 14/1/2026
A89: https://www.businesswebmarks.com/ | B89: 88 | C89: 76 | E89: https://www.businesswebmarks.com/best-investment-company-in-hyderabad-how-to-choose-the-right-partner-for-your-financial-growth/
A90: https://www.legacydirectory.com/ | B90: 15 | C90: 23 | E90: https://www.legacydirectory.com/best-investment-company-in-hyderabad-how-to-choose-the-right-partner-for-your-financial-growth/
A91: https://www.mbookmarking.com/ | B91: 62 | C91: 58 | E91: https://www.mbookmarking.com/story/best-investment-company-in-hyderabad-how-to-choose-the-right-partner-for-your-financial-
A92: https://www.starbookmarking.com/ | B92: 29 | C92: 50 | E92: https://www.starbookmarking.com/story/fund-management-services-in-hyderabad
A93: https://www.freebookmarkingsite.com/ | B93: 44 | C93: 65 | E93: https://www.freebookmarkingsite.com/story/top-venture-capital-firms-in-hyderabad
A94: https://www.social-bookmarkingsites.com/ | B94: 76 | C94: 63 | E94: https://www.social-bookmarkingsites.com/story/business-investors-in-hyderabad-investors-clubs
A95: https://www.sbookmarking.com/ | B95: 54 | C95: 42 | E95: https://www.sbookmarking.com/story/micro-macro-investments-in-hyderabad
A96: https://ritzgroup.livepositively.com/ | B96: 47 | C96: 56 | E96: https://ritzgroup.livepositively.com/best-investment-company-in-hyderabad-how-to-choose-the-right-partner-for-your-financial-growth
A97: 16/1/2026
A98: https://www.freewebmarks.com/ | B98: 83 | C98: 66 | E98: https://www.freewebmarks.com/story/best-investment-company-in-india-choose-the-right-partner-for-wealth-growth
A99: https://www.social-bookmarkingsites.com/ | B99: 84 | C99: 63 | E99: https://www.social-bookmarkingsites.com/story/best-investment-company-in-india-choose-the-right-partner-for-wealth-growth
A100: https://www.peoplebookmarks.com/ | B100: 44 | C100: 44 | E100: https://www.peoplebookmarks.com/best-investment-company-in-india-choose-the-right-partner-for-wealth-growth/
...

Sheet Directorites Submissions
A1: Referring URl | B1: DA | C1: PA | D1: Type of Submission | E1: Submitted URl | F1: Status
A2: https://caida.eu/ | B2: 17 | C2: 45 | D2: Directories | E2: https://caida.eu/submit.php
A3: https://www.fire-directory.com/ | B3: 32 | C3: 51 | D3: Directories | E3: https://www.fire-directory.com/submit.php | G3: Gmail | H3: Password
A4: https://www.craigslist.org/ | B4: 88 | C4: 76 | D4: Directories | E4: https://hyderabad.craigslist.org/fns/d/how-to-choose-the-right-investment/7904178770.html | G4: ritzgroupco123@gmail.com | H4: Ritzgroup@1122
A5: https://linkdirectorylistings.org/ | B5: 73 | C5: 42 | D5: Directories | E5: https://linkdirectorylistings.org/submit-site/
A6: https://www.dizila.com/ | B6: 17 | C6: 45 | D6: Directories | E6: https://www.dizila.com/submit?c=27&LINK_TYPE=1
A7: 24/12/2025
A8: https://www.firstlinkonline.info/ | B8: 65 | C8: 39 | D8: Directories | E8: https://www.firstlinkonline.info/submit.php?c=702&LINK_TYPE=8
A9: https://www.qualityinternetdirectory.com | B9: 20 | C9: 44 | D9: Directories | E9: https://www.qualityinternetdirectory.com/submit.php
A10: https://www.freeprwebdirectory.com | B10: 15 | C10: 50 | D10: Directories | E10: https://www.freeprwebdirectory.com/submit.php
A11: https://www.submissionwebdirectory.com | B11: 28 | C11: 28 | D11: Directories | E11: https://www.submissionwebdirectory.com/submit.php
A12: https://www.prolinkdirectory.com/ | B12: 34 | C12: 67 | D12: Directories | E12: https://www.prolinkdirectory.com/submit.php
A13: 29/12/2025
A14: https://www.247webdirectory.com/ | B14: 24 | C14: 51 | E14: https://www.247webdirectory.com/?aspxerrorpath=/save.aspx
A15: https://www.ecobluedirectory.com/ | B15: 31 | C15: 45 | E15: https://www.ecobluedirectory.com/submit.php
A16: https://www.greenydirectory.com/ | B16: 22 | C16: 44 | E16: https://www.greenydirectory.com/submit.php
A17: https://www.reddit-directory.com/ | B17: 32 | C17: 46 | E17: https://www.reddit-directory.com/submit.php
A18: https://www.jayde.com/ | B18: 41 | C18: 56 | E18: https://www.jayde.com/landing.html
A19: 30/12/2025
A20: https://www.groovy-directory.com/ | B20: 13 | C20: 39 | E20: https://www.groovy-directory.com/submit.php
A21: https://www.craigslistdirectory.net/ | B21: 19 | C21: 41 | E21: https://www.bluesparkledirectory.com/submit.php
A22: https://alive-directory.com/ | B22: 78 | C22: 63 | E22: https://alive-directory.com/submit.php
A23: https://www.submissionwebdirectory.com | B23: 54 | C23: 42 | E23: https://www.submissionwebdirectory.com/submit.php
A24: https://www.cipinet.com/ | B24: 73 | C24: 52 | E24: https://www.cipinet.com/Business/Financial_Services/
A25: https://www.highrankdirectory.com/ | B25: 65 | C25: 85 | E25: https://www.highrankdirectory.com/submit.php?id=671
A26: https://localpages.com/ | B26: 47 | C26: 33 | E26: https://localpages.com/business-listing
A27: 31/12/2025
A28: https://www.qualityinternetdirectory.com | B28: 20 | C28: 44 | E28: https://www.qualityinternetdirectory.com/submit.php
A29: https://www.freeprwebdirectory.com | B29: 15 | C29: 50 | E29: https://www.firstlinkonline.info/submit.php?c=702&LINK_TYPE=8
A30: https://www.submissionwebdirectory.com | B30: 28 | C30: 28 | E30: https://www.freeprwebdirectory.com/submit.php
A31: https://www.bluebook-directory.com/ | B31: 32 | C31: 51 | E31: https://www.bluebook-directory.com/submit.php
A32: https://www.interesting-dir.com/ | B32: 34 | C32: 67 | E32: https://www.interesting-dir.com/submit.php
A33: 46054
A34: https://www.canadawebdir.com/ | B34: 82 | C34: 69 | E34: https://www.canadawebdir.com/submit.php
A35: https://www.canadiandirectory.org/ | B35: 25 | C35: 42 | E35: https://www.canadiandirectory.org/submit.php
A36: https://www.gtawebdirectory.com/ | B36: 58 | C36: 58 | E36: https://www.gtawebdirectory.com/submit.php
A37: https://www.fire-directory.com/ | B37: 48 | C37: 50 | E37: https://www.fire-directory.com/submit.php
A38: https://www.submissionwebdirectory.com/ | B38: 44 | C38: 49 | E38: https://www.submissionwebdirectory.com/submit.php
A39: https://www.fire-directory.com/ | B39: 44 | C39: 49 | E39: https://www.fire-directory.com/submit.php
A40: 46143
A41: https://www.prolinkdirectory.com/ | B41: 34 | C41: 45 | E41: https://www.prolinkdirectory.com/submit.php
A42: https://www.bing-directory.com | B42: 45 | C42: 34 | E42: https://www.bing-directory.com/submit.php
A43: https://www.interesting-dir.com/ | B43: 34 | C43: 67 | E43: https://www.interesting-dir.com/submit.php
A44: http://lemon-directory.com/ | B44: 47 | C44: 26 | E44: http://lemon-directory.com/submit.php
A45: https://www.cipinet.com/ | B45: 43 | C45: 64 | E45: https://www.cipinet.com/adv.php
A46: 46174
A47: https://www.ourdirectory.info/submit.php | B47: 25 | C47: 42 | E47: https://www.ourdirectory.info/submit.php?c=702&LINK_TYPE=8
A48: https://www.submissionwebdirectory.com/ | B48: 58 | C48: 58 | E48: https://www.submissionwebdirectory.com/submit.php
A49: https://www.highrankdirectory.com/ | B49: 48 | C49: 50 | E49: https://www.highrankdirectory.com/submit.php
A50: https://www.ask-directory.com/ | B50: 44 | C50: 49 | E50: https://www.ask-directory.com/submit.php
A51: http://www.addirectory.org/ | B51: 44 | C51: 49 | E51: http://www.addirectory.org/submit.php
A52: 46204
A53: http://24directory.com.ar/ | B53: 66 | C53: 61 | E53: http://24directory.com.ar/submit.php?c=689&LINK_TYPE=8
A54: http://www.corpdirectory.info/ | B54: 70 | C54: 50 | E54: http://www.corpdirectory.info/submit.php?c=689&LINK_TYPE=2
A55: https://www.prolinkdirectory.com/ | B55: 89 | C55: 68 | E55: https://www.prolinkdirectory.com/submit.php
A56: https://www.fire-directory.com/ | B56: 55 | C56: 85 | E56: https://www.fire-directory.com/submit.php
A57: https://poordirectory.com/ | B57: 28 | C57: 40 | E57: https://poordirectory.com/submit.php
A58: 46235
A59: https://www.prolinkdirectory.com/ | B59: 81 | C59: 59 | E59: https://www.prolinkdirectory.com/submit.php
A60: https://www.ukinternetdirectory.net/ | B60: 28 | C60: 40 | E60: https://www.ukinternetdirectory.net/submit.php
A61: https://www.britainbusinessdirectory.com/ | B61: 84 | C61: 55 | E61: https://www.britainbusinessdirectory.com/submit.php
A62: https://poordirectory.com | B62: 90 | C62: 77 | E62: https://poordirectory.com/submit.php
A63: http://lemon-directory.com/ | B63: 18 | C63: 40 | E63: http://lemon-directory.com/submit.php
A64: 46266
A65: https://www.alive-directory.com/ | B65: 28 | C65: 40 | E65: https://www.alive-directory.com/submit.php
A66: https://reddit-directory.com/ | B66: 84 | C66: 55 | E66: https://reddit-directory.com/submit.php
A67: https://www.promotebusinessdirectory.com/ | B67: 90 | C67: 77 | E67: https://www.promotebusinessdirectory.com/submit.php?c=39&LINK_TYPE=2
A68: https://homedirectory.biz/ | B68: 18 | C68: 40 | E68: https://homedirectory.biz/submit.php
A69: https://www.247webdirectory.com | B69: 50 | C69: 58 | E69: https://www.247webdirectory.com/?aspxerrorpath=/save.aspx
A70: https://www.allstatesusadirectory.com/ | B70: 47 | C70: 63 | E70: https://www.allstatesusadirectory.com/submit.php
A71: 46357
A72: https://www.prolinkdirectory.com/ | B72: 84 | C72: 63 | E72: https://www.prolinkdirectory.com/article-payment.php?id=69208
A73: https://www.1websdirectory.com/ | B73: 44 | C73: 44 | E73: https://www.1websdirectory.com/thank-you-free-submit/
A74: https://www.submissionwebdirectory.com/ | B74: 66 | C74: 61 | E74: https://www.submissionwebdirectory.com/submit.php
A75: https://www.highrankdirectory.com/ | B75: 70 | C75: 50 | E75: https://www.highrankdirectory.com/submit.php
A76: https://www.ask-directory.com/ | B76: 89 | C76: 68 | E76: https://www.ask-directory.com/submit.php
A77: 13/1/2026
A78: https://www.usalistingdirectory.com/ | B78: 14 | C78: 40 | E78: https://www.usalistingdirectory.com/submit.php
A79: https://www.247webdirectory.com/ | B79: 15 | C79: 41 | E79: https://www.247webdirectory.com/?aspxerrorpath=/save.aspx
A80: https://www.freeprwebdirectory.com/ | B80: 25 | C80: 45 | E80: https://www.freeprwebdirectory.com/submit.php
A81: https://linkdirectorylistings.org/ | B81: 16 | C81: 41 | E81: https://linkdirectorylistings.org/submit-site/
A82: https://fWebDirectory.com/ | B82: 22 | C82: 41 | E82: https://fWebDirectory.com/464/posts/3/20/1948041.html
A83: https://www.qualityinternetdirectory.com/ | B83: 14 | C83: 42 | E83: https://www.qualityinternetdirectory.com/submit.php
A84: https://www.siteswebdirectory.com/ | B84: 23 | C84: 43 | E84: https://www.siteswebdirectory.com/submit.php?c=1623&LINK_TYPE=2
A85: https://www.qualityinternetdirectory.com/ | B85: 17 | C85: 38 | E85: https://www.qualityinternetdirectory.com/submit.php
A86: https://www.sitepromotiondirectory.com/ | B86: 56 | C86: 74 | E86: https://www.sitepromotiondirectory.com/submit.php
A87: 14/1/2026
A88: https://www.ourdirectory.info/ | B88: 52 | C88: 55 | E88: https://www.ourdirectory.info/submit.php?c=702&LINK_TYPE=8
A89: https://www.jasminedirectory.com/ | B89: 69 | C89: 53 | E89: https://www.jasminedirectory.com/index.php?a=2070753691
A90: https://www.lemon-directory.com/ | B90: 18 | C90: 39 | E90: https://www.lemon-directory.com/submit.php
A91: https://www.sitepromotiondirectory.com | B91: 28 | C91: 50 | E91: https://www.sitepromotiondirectory.com/submit.php
A92: https://www.usalistingdirectory.com | B92: 12 | C92: 41 | E92: https://www.usalistingdirectory.com/submit.php
A93: https://www.alive-directory.com/ | E93: https://www.alive-directory.com/submit.php
A94: 16/1/2026
A95: http://24directory.com.ar/ | B95: 83 | C95: 66 | E95: http://24directory.com.ar/submit.php?c=702&LINK_TYPE=8
A96: https://caida.eu/ | B96: 84 | C96: 63 | E96: https://caida.eu/submit.php
A97: https://www.prolinkdirectory.com/ | B97: 44 | C97: 44 | E97: https://www.prolinkdirectory.com/submit.php
A98: https://www.canadiandirectory.org/ | B98: 66 | C98: 61 | E98: https://www.canadiandirectory.org/submit.php
A99: https://www.gtawebdirectory.com/ | B99: 70 | C99: 50 | E99: https://www.gtawebdirectory.com/submit.php
A100: https://www.fire-directory.com/ | B100: 89 | C100: 68 | E100: https://www.fire-directory.com/submit.php
...

Sheet Classifieds Submissions
A1: Referring URl | B1: DA | C1: PA | D1: Type of Submission | E1: Submitted URl | F1: Status
A2: https://www.locanto.org | B2: 15 | C2: 23 | D2: Clasifieds | E2: https://www.locanto.org/nanakramguda/ID_8111869115/How-to-Choose-the-Right-Investment-Company-for-Long-Term-Wealth.html | H2: Gmail | I2: Password
A3: https://www.freeclassifiedssites.com/ | B3: 29 | C3: 50 | D3: Clasifieds | E3: https://www.freeclassifiedssites.com/index.php?view=post&cityid=609&lang=en&catid=12&subcatid=82&shortcutregion=& | H3: ritzgroupco123@gmail.com | I3: Ritzgroup@1122
A4: https://hyderabad.indads.in/ | B4: 20 | C4: 34 | D4: Clasifieds | E4: https://hyderabad.indads.in/item/1370065/
A5: https://hyderabad.classifiedsfactor.com/ | B5: 26 | C5: 29 | D5: Clasifieds | E5: https://items.classifiedsfactor.com/post-a-classified-ad-type.php
A6: https://www.advertiseera.com | B6: 22 | C6: 44 | D6: Clasifieds | E6: https://www.advertiseera.com/post-an-ad-step-6.php
A7: 24/12/2025
A8: https://indianapolis.claz.org/ | B8: 23 | C8: 43 | D8: Clasifieds | E8: https://indianapolis.claz.org/classifieds/services/finance/l272bbmn8a6xr-best-investment-company-in-india
A9: https://www.classifiedads.com | B9: 61 | C9: 35 | D9: Clasifieds | E9: https://www.classifiedads.com/financial_services/688z5knvb3dx9
A10: https://chennaiclassic.com/ | B10: 19 | C10: 48 | D10: Clasifieds | E10: https://chennaiclassic.com/listing/best-investment-company-in-india/
A11: https://www.yookalo.com | B11: 75 | C11: 86 | D11: Clasifieds | E11: https://www.yookalo.com/item-success
A12: 29/12/2025
A13: freeadsincanada.com | B13: 23 | C13: 43 | E13: http://andhra-pradesh.freeadsinindia.in/en-i-editResourceOffer-i-id-i-3212786-i-best-investment-company-in-india-ritzgroup.html
A14: https://www.canadianplanet.net | B14: 26 | C14: 50 | E14: https://www.canadianplanet.net/ritzgroup-investment-organization-F1108C1061BD54C
A15: https://www.classifiedsfactor.com/ | B15: 35 | C15: 56 | E15: https://items.classifiedsfactor.com/post-a-classified-ad-type.php
A16: https://www.topfreeclassifieds.com | B16: 14 | C16: 29 | E16: https://www.topfreeclassifieds.com/index.php?view=post&cityid=16&lang=en&catid=12&subcatid=82&shortcutregion=&
A17: https://indiadial.in | B17: 14 | C17: 26 | E17: https://indiadial.in/services/finance-legal/financial-advice/best-investment-company-in-india-291425.html
A18: 30/12/2025
A19: https://www.locanto.org | B19: 15 | C19: 23 | E19: https://www.locanto.org/nanakramguda/ID_8129985068/Ritz-Group-GreenTech-FinTech-HealthTech-Investments-Buildi.html
A20: https://hyderabad.craigslist.org/ | B20: 88 | C20: 67 | E20: https://hyderabad.craigslist.org/fns/d/ritz-group-greentech-fintech-healthtech/7905429805.html
A21: https://hyderabad.indads.in/ | B21: 20 | C21: 34 | E21: https://hyderabad.indads.in/item/1372245/
A22: https://www.freeclassifiedssites.com/ | B22: 29 | C22: 50 | E22: https://www.freeclassifiedssites.com/index.php?view=post&cityid=609&lang=en&catid=12&subcatid=82&shortcutregion=&
A23: https://GlobalClassified.net/ | B23: 33 | C23: 29 | E23: https://GlobalClassified.net/464/posts/3/20/1964125.html
A24: 31/12/2025
A25: https://in.classi4u.com/ | B25: 88 | C25: 76 | E25: https://in.classi4u.com/p/hyderabad-best-investment-company-in-india-pid4370501
A26: https://www.yookalo.com | B26: 75 | C26: 86 | E26: https://www.yookalo.com/item/new?e=team@ritzgroup.co
A27: https://eonlineads.com/ | B27: 21 | C27: 45 | E27: https://eOnlineAds.com/464/posts/3/20/1834908.html
A28: https://unolist.in/ | B28: 34 | C28: 55 | E28: https://unolist.in/desc/744213_Best-Investment-Company-in-India.html
A29: https://www.vivastreet.co.in/ | B29: 55 | C29: 28 | E29: https://www.vivastreet.co.in/user/account/ads
A30: https://www.adpost.com/ | B30: 44 | C30: 84 | E30: https://www.adpost.com/in/business_opportunities/484675/
A31: 46054
A32: https://www.topclassifieds.com/a | B32: 82 | C32: 69 | E32: https://www.topclassifieds.com/ads/16/posts/16-Services/144-Financial/5512955-Best-Investment-Company-in-India.html
A33: https://FreeWebAds.biz/ | B33: 25 | C33: 42 | E33: https://FreeWebAds.biz/464/posts/3/20/1857162.html
A34: https://www.locanto.org/ | B34: 58 | C34: 58 | E34: https://www.locanto.org/nanakramguda/ID_8137941986/Top-Venture-Capital-Firms-in-India-2025.html
A35: https://www.wallclassifieds.com/ | B35: 48 | C35: 50 | E35: https://www.wallclassifieds.com/post-a-free-ad-process-phone.php
A36: https://hyderabad.craigslist.org/ | B36: 44 | C36: 49 | E36: https://hyderabad.craigslist.org/fns/d/top-venture-capital-firms-in-india-2025/7905986089.html
A37: https://Classified4Free.net/ | B37: 35 | C37: 56 | E37: https://Classified4Free.net/464/posts/3/20/1812057.html
A38: 46143
A39: https://unolist.in/ | B39: 88 | C39: 67 | E39: https://unolist.in/desc/744923_Best-Investment-Company-in-India.html
A40: claz.org | B40: 20 | C40: 34 | E40: https://indianapolis.claz.org/classifieds/services/finance/l27cip4yjtfg0-business-investors-in-india-why
A41: https://www.wallclassifieds.com/ | B41: 55 | C41: 63 | E41: https://www.wallclassifieds.com/post-a-free-ad-process-phone.php
A42: https://www.webclassifieds.us/ | B42: 64 | C42: 45 | E42: https://www.webclassifieds.us/forum/threads/business-investors-in-india-why-joining-investors-clubs-is-the-smartest-move-in-2026.89039/
A43: 45809
A44: https://www.adclassified.in/ | B44: 88 | C44: 76 | E44: https://www.adclassified.in/jobs/real-estate/best-investment-company-in-india_i34709
A45: https://www.elzse.com/ | B45: 15 | C45: 23 | E45: https://www.elzse.com/best-investment-company-in-india-i202436
A46: https://www.hotfreelist.com | B46: 62 | C46: 58 | E46: https://www.hotfreelist.com/index.php?view=post&cityid=46&lang=en&catid=2&subcatid=20&shortcutregion=0&
A47: https://Classified4Free.net/ | B47: 29 | C47: 50 | E47: https://Classified4Free.net/464/posts/3/20/1814501.html
A48: https://items.classifiedsfactor.com/ | B48: 25 | C48: 30 | E48: https://items.classifiedsfactor.com/post-a-classified-ad-type.php
A49: 46204
A50: https://items.classifiedsfactor.com/ | B50: 80 | C50: 50 | E50: https://items.classifiedsfactor.com/post-a-classified-ad-type.php
A51: https://www.wallclassifieds.com/ | B51: 43 | C51: 54 | E51: https://www.wallclassifieds.com/post-a-free-ad-process-phone.php
A52: https://www.classifiedads.com/ | B52: 59 | C52: 51 | E52: https://www.classifiedads.com/financial_services/2b8bhdqcr3dx8
A53: 46235
A54: https://www.locanto.co.uk/ | B54: 90 | C54: 77 | E54: https://www.locanto.co.uk/colchester/ID_8156270254/Top-Fund-Management-Services-in-India-Features-Benefits-How.html
A55: https://www.topclassifieds.com/ | B55: 18 | C55: 40 | E55: https://www.topclassifieds.com/ads/16/posts/12/82/5516156.html
A56: https://adfreeposting.com/ | B56: 50 | C56: 58 | E56: https://adfreeposting.com/en/listing/best-investment-company-in-india
A57: 46266
A58: https://items.classifiedsfactor.com/ | B58: 61 | C58: 44 | E58: https://items.classifiedsfactor.com/post-a-classified-ad-type.php
A59: https://hyderabad.craigslist.org/ | B59: 54 | C59: 52 | E59: https://hyderabad.craigslist.org/fns/d/best-investment-company-in-hyderabad/7907490841.html
A60: https://adsmantra.com/ | B60: 59 | C60: 51 | E60: https://adsmantra.com/posting.do
A61: https://www.adpost.com/ | B61: 81 | C61: 59 | E61: https://www.adpost.com/in/business_opportunities/484994/
A62: 46357
A63: https://Classified4Free.net/ | B63: 73 | C63: 43 | E63: https://Classified4Free.net/464/posts/3/20/1818337.html
A64: https://www.freeclassifiedssites.com/ | B64: 50 | C64: 58 | E64: https://www.freeclassifiedssites.com/index.php?view=post&cityid=609&lang=en&catid=12&subcatid=82&shortcutregion=&
A65: https://www.wallclassifieds.com/ | B65: 41 | C65: 41 | E65: https://www.wallclassifieds.com/post-a-free-ad-process-phone.php
A66: https://www.locanto.com/ | B66: 70 | C66: 57 | E66: https://www.locanto.com/towson/ID_8167530821/Top-Fund-Management-Services-in-India-How-to-Grow-Your-Wealth-S.html
A67: https://www.adpost.com/ | B67: 35 | C67: 34 | E67: https://www.adpost.com/in/business_opportunities/485069/
A68: 13/1/2026
A69: https://www.topclassifieds.com/ | B69: 94 | C69: 84 | E69: https://www.topclassifieds.com/ads/index.php?view=post&cityid=16&lang=en&catid=12&subcatid=82&shortcutregion=&
A70: https://items.classifiedsfactor.com/ | B70: 79 | C70: 66 | E70: https://items.classifiedsfactor.com/post-a-classified-ad-type.php
A71: https://Classifieds4Free.biz/ | B71: 13 | C71: 27 | E71: https://Classifieds4Free.biz/464/posts/3/20/1952621.html
A72: https://www.wallclassifieds.com/ | B72: 54 | C72: 52 | E72: https://www.wallclassifieds.com/post-a-free-ad-process-phone.php
A73: https://GlobalClassified.net/ | B73: 53 | C73: 62 | E73: https://GlobalClassified.net/464/posts/3/20/1982135.html
A74: 14/1/2026
A75: https://www.adclassified.in/ | B75: 44 | C75: 67 | E75: https://www.adclassified.in/jobs/real-estate/best-investment-company-in-hyderabad_i35602
A76: https://Classified4Free.net/ | B76: 32 | C76: 52 | E76: https://Classified4Free.net/464/posts/3/20/1820012.html
A77: https://ezclassifiedads.com/ | B77: 65 | C77: 85 | E77: https://ezclassifiedads.com/464/posts/3/20/1902740.html
A78: https://www.freeclassifiedssites.com | B78: 74 | C78: 68 | E78: https://www.freeclassifiedssites.com/index.php?view=post&cityid=609&lang=en&catid=12&subcatid=82&shortcutregion=&
A79: 16/1/2026
A80: https://globalclassified.net/ | B80: 94 | C80: 86 | E80: https://globalclassified.net/index.php?view=post&cityid=464&lang=en&catid=3&subcatid=20&shortcutregion=0&
A81: https://www.locanto.org/ | B81: 52 | C81: 55 | E81: https://www.locanto.org/hyderabad/ID_8180968307/Fund-Management-services-in-hyderabad.html
A82: https://hyderabad.craigslist.org/ | B82: 94 | C82: 83 | E82: https://hyderabad.craigslist.org/fns/d/best-investment-company-in-hyderabad/7908991242.html
A83: https://items.classifiedsfactor.com/ | B83: 92 | C83: 71 | E83: https://items.classifiedsfactor.com/post-a-classified-ad-type.php
A84: https://ezclassifiedads.com/ | B84: 68 | C84: 68 | E84: https://ezclassifiedads.com/464/posts/3/20/1905233.html
A85: https://Classified4Free.net/ | B85: 92 | C85: 72 | E85: https://Classified4Free.net/464/posts/3/20/1821362.html
A86: 19/1/2026
A87: https://Classified4Free.net/ | B87: 57 | C87: 61 | E87: https://Classified4Free.net/464/posts/3/20/1822815.html
A88: https://items.classifiedsfactor.com/ | B88: 31 | C88: 50 | E88: https://items.classifiedsfactor.com/post-a-classified-ad-type.php
A89: https://Classifieds4Free.biz/ | B89: 14 | C89: 38 | E89: https://Classifieds4Free.biz/464/posts/3/20/1960669.html
A90: https://www.wallclassifieds.com/ | B90: 52 | C90: 55 | E90: https://www.wallclassifieds.com/post-a-free-ad-process-phone.php
A91: https://GlobalClassified.net/ | B91: 69 | C91: 53 | E91: https://GlobalClassified.net/464/posts/3/20/1990183.html
A92: https://classifieds4free.biz/ | B92: 18 | C92: 39 | E92: https://classifieds4free.biz/index.php?view=post&cityid=464&lang=en&catid=3&subcatid=20&shortcutregion=0&
A93: https://classifiedz.in/0 | B93: 28 | C93: 50 | E93: https://classifiedz.in/real-estate/flat-apartments-for-rent/best-investment-company-in-india_i464830
A94: 20/1/2026
A95: https://Classifieds4Free.biz | B95: 73 | C95: 57 | E95: https://Classifieds4Free.biz/464/posts/3/20/1962425.html
A96: https://www.heroclassifieds.com/ | B96: 15 | C96: 37 | E96: https://www.heroclassifieds.com/?post_type=listivo_listing&p=11102&preview=true
A97: https://globalclassified.net/ | B97: 24 | C97: 49 | E97: https://globalclassified.net/index.php?view=post&cityid=464&lang=en&catid=3&subcatid=20&shortcutregion=0&
A98: https://hyderabad.craigslist.org | B98: 55 | C98: 67 | E98: https://hyderabad.craigslist.org/fns/d/best-investment-company-in-hyderabad/7909828214.html
A99: 21/1/2026
A100: https://ezclassifiedads.com/ | B100: 44 | C100: 65 | E100: https://ezclassifiedads.com/464/posts/3/20/1912818.html
...

Sheet Artical Submissions
A1: Referring URl | B1: DA | C1: PA | D1: Type of Submission | E1: Submitted URl | F1: Status
A2: https://articlebiz.com/ | B2: 46 | C2: 53 | E2: https://articlebiz.com/checkArticle/statuses/ritzgroupco123%40gmail.com
A3: articlealley.com | B3: 53 | C3: 52 | E3: https://www.articlealley.com/list/best-investment-company-in-india-82825
A4: https://blog.freeadstime.org | B4: 37 | C4: 48 | E4: https://blogpost.freeadstime.org/post-an-article-steps.php
A5: 31/12/2025
A6: https://article.advertiseera.com/ | B6: 22 | C6: 19 | E6: https://article.advertiseera.com/article-submitted/
A7: 27/1/2026
A8: https://articlebiz.com/ | E8: https://articlebiz.com/checkArticle/statuses/team%40ritzgroup.co
A9: https://article.advertiseera.com/ | E9: https://article.advertiseera.com/article-submitted/
A10: 46328
A11: https://www.webdirectoryhealth.com/ | E11: https://www.webdirectoryhealth.com/submit_article.php
A12: https://articles.abilogic.com/ | E12: https://articles.abilogic.com/myaccount/articles/manage/1/1/
A13: https://articlebiz.com/checkArticle/ | E13: https://articlebiz.com/checkArticle/statuses/ritzgroupco123%40gmail.com
A14: 16/02/2026
A15: https://www.marketinginternetdirectory.com/ | B15: 30 | C15: 47 | E15: https://www.marketinginternetdirectory.com/submit_article.php
A16: https://promotebusinessdirectory.com/ | B16: 25 | C16: 25 | E16: https://promotebusinessdirectory.com/article_payment.php?id=10937239
A17: https://www.highrankdirectory.com/ | B17: 41 | C17: 45 | E17: https://www.highrankdirectory.com/submit_article.php
A18: https://www.siteswebdirectory.com | B18: 48 | C18: 28 | E18: https://www.siteswebdirectory.com/submit_article.php
A19: https://www.freeprwebdirectory.com | B19: 55 | C19: 34 | E19: https://www.freeprwebdirectory.com/submit_article.php
A20: https://www.theseobacklink.com/ | B20: 26 | C20: 28 | E20: https://www.theseobacklink.com/submit-article
A21: 17/02/2026
A22: https://www.freeprwebdirectory.com/ | B22: 55 | C22: 34 | E22: https://www.freeprwebdirectory.com/submit_article.php
A23: https://www.usalistingdirectory.com/ | B23: 31 | C23: 48 | E23: https://www.usalistingdirectory.com/submit_article.php
A24: https://ritzgroup.livepositively.com/ | B24: 61 | C24: 57 | E24: https://ritzgroup.livepositively.com/why-ritz-group-is-investing-in-greentech-fintech-and-healthtech-for-a-better-tomorrow
A25: https://theomnibuzz.com/ | B25: 58 | C25: 52 | E25: https://theomnibuzz.com/best-investment-company-in-india--how-to-choose-the-right-partner-for-your-financial-growtht-titl
A26: 19/02/2026
A27: https://ritzgroup.livepositively.com/ | B27: 61 | C27: 57 | E27: https://ritzgroup.livepositively.com/business-investors-and-investor-clubs-a-complete-guide-to-funding-and-wealth-creation
A28: https://theomnibuzz.com/ | B28: 58 | C28: 52 | E28: https://theomnibuzz.com/business-investors---investor-clubs--a-complete-guide-to-funding-and-wealth-creation
A29: https://www.freeprwebdirectory.com/ | B29: 55 | C29: 34 | E29: https://www.freeprwebdirectory.com/submit_article.php
A30: https://www.usalistingdirectory.com/ | B30: 31 | C30: 48 | E30: https://www.usalistingdirectory.com/submit_article.php
A31: https://articles.h1ad.com/ | E31: https://articles.h1ad.com/article-submitted/
A32: 20/02/2026
A33: https://www.marketinginternetdirectory.com/ | B33: 30 | C33: 47 | E33: https://www.marketinginternetdirectory.com/submit_article.php
A34: https://promotebusinessdirectory.com/ | B34: 25 | C34: 25 | E34: https://promotebusinessdirectory.com/article_payment.php?id=10951186
A35: https://www.highrankdirectory.com/ | B35: 41 | C35: 45 | E35: https://www.highrankdirectory.com/submit_article.php
A36: https://www.highrankdirectory.com/ | B36: 50 | C36: 31 | E36: https://www.highrankdirectory.com/submit_article.php
A37: https://www.siteswebdirectory.com | B37: 48 | C37: 28 | E37: https://www.siteswebdirectory.com/submit_article.php
A38: https://www.theseobacklink.com/ | B38: 26 | C38: 28 | E38: https://www.theseobacklink.com/submit-article
A39: https://fWebDirectory.com/ | B39: 32 | C39: 25 | E39: https://fWebDirectory.com/464/posts/3/20/2002466.html

Sheet Pdf Submissions
A1: Referring URl | B1: DA | C1: PA | D1: Type of Submission | E1: Submitted URl | F1: Status
A2: http://www.pinpdf.com/ | B2: 31 | C2: 37 | E2: https://pinpdf.com/best-investment-company-in-india-466f1065019d54dc0318ac914b162031.html
A3: www.slideshare.net | B3: 94 | C3: 86 | E3: https://www.slideshare.net/slideshow/ritz-group-greentech-fintech-healthtech-investments/284886954 | G3: Gmail | H3: Password
A4: dochub.com | B4: 60 | C4: 58 | E4: https://www.docdroid.com/lEnO9Ck/off-page-pdf | G4: ritzgroupco123@gmail.com | H4: Ritzgroup@1122
A5: issuu.com | B5: 94 | C5: 83 | E5: https://issuu.com/ritzgroup/docs/best_investment_company_in_india
A6: www.smallpdf.com | B6: 72 | C6: 57 | E6: https://smallpdf.com/edit-pdf#r=result&t=c5990256934f1f401f3eb65b4b5d8531&i=annotate
A7: dochub.com | B7: 60 | C7: 58 | E7: https://dochub.com/ritz-group/7vA0q9lw2bQnPZEwPDNOxd/off-page-1-pdf?pg=3
A8: https://www.4shared.com/ | B8: 94 | C8: 74 | E8: https://www.4shared.com/web/preview/pdf/MygdS0wJjq?
A9: https://www.scribd.com | B9: 45 | C9: 66 | E9: https://www.scribd.com/document/974003863/Best-Investment-Company-in-India?secret_password=49Q5Kbw04xBjl3iLCEsn
A10: https://www.pdfhost.net/ | B10: 79 | C10: 62 | E10: https://www.pdfhost.net/index.php?Action=UploadFile
A11: 31/12/2025
A12: www.degoo.com | B12: 55 | C12: 44 | E12: https://app.degoo.com/files/0?ID=20808314304
A13: www.dochub.com | B13: 60 | C13: 53 | E13: https://dochub.com/ritz-group/JWop0ZAKk8YLdllVrYa9GP/off-page-pdf
A14: https://www.scribd.com | B14: 45 | C14: 66 | E14: https://www.scribd.com/document/974347597/Fund-Management-services-in-India?secret_password=IfX4HthRAlqpFwiWuazn
A15: https://archive.org | B15: 94 | C15: 84 | E15: https://archive.org/details/httpsritzgroup.co
A16: 46143
A17: https://workupload.com/ | B17: 73 | C17: 57 | E17: https://workupload.com/file/LhKhcE73NbB
A18: https://limewire.com/ | B18: 15 | C18: 37 | E18: https://limewire.com/
A19: https://dochub.com/ | B19: 24 | C19: 49 | E19: https://dochub.com/ritz-group/JWop0ZAKk8Y0Je1VrYa9GP/off-page-2-pdf
A20: https://pinpdf.com | B20: 24 | C20: 49 | E20: https://pinpdf.com/top-venture-capital-firms-in-india-2025-3cb9450cfd8c695cb139c8db6d8b1e6c.html
A21: www.tiiny.hostpdf-upload | B21: 25 | C21: 30 | E21: https://black-kelley-30.tiiny.site/
A22: https://files.fm/ | B22: 27 | C22: 38 | E22: https://files.fm/u/mndntxkfzz#/view/q96pg2btkw
A23: https://smallpdf.com/ | B23: 45 | C23: 65 | E23: https://smallpdf.com/pdf-ocr#r=result&t=e935dea3a00101412023f0164fb8cab5&i=ocr
A24: 46204
A25: https://www.4shared.com/ | B25: 94 | C25: 74 | E25: https://www.4shared.com/web/preview/pdf/SA2JaRaiku?
A26: 46266
A27: https://workupload.com/file/nU4Lkj9L24Q | B27: 44 | C27: 67 | E27: https://workupload.com/file/nU4Lkj9L24Q
A28: https://limewire.com/ | B28: 58 | C28: 86 | E28: https://limewire.com/?referrer=cwnprhcil4
A29: https://issuu.com/home/ | B29: 38 | C29: 54 | E29: https://issuu.com/home/docs/eud6y3h9cku/share?post_publish=true
A30: 46357
A31: https://www.4shared.com/ | B31: 43 | C31: 66 | E31: https://www.4shared.com/account/home.jsp#dir=jZuwJ9pJ
A32: https://smallpdf.com/ | B32: 32 | C32: 47 | E32: https://smallpdf.com/pdf-to-jpg#r=result&t=28c11b2a593da939c77b57ee7cba833f&i=convert-to-image
A33: 28/1/2026
A34: http://www.pinpdf.com/ | B34: 31 | C34: 37 | E34: https://pinpdf.com/investment-strategies-for-smart-wealth-creation-a-complete-g-3c728023e7922d594dd29f89e421db
A35: www.slideshare.net | B35: 94 | C35: 86 | E35: https://www.slideshare.net/slideshow/investment-strategies-for-smart-wealth-creation-a-complete-guide-for-modern-investors/285613892#1
A36: dochub.com | B36: 60 | C36: 58 | E36: https://dochub.com/ritz-group/5lae27DR5qaZMNrRmqjZv1/off-page-pdf
A37: issuu.com | B37: 94 | C37: 83 | E37: https://issuu.com/ritzgroup/docs/off_-_page_
A38: www.smallpdf.com | B38: 72 | C38: 57 | E38: https://smallpdf.com/edit-pdf#r=result&t=6a13bdd8d12964a22af692da510511b2&i=annotate
A39: https://www.4shared.com/ | B39: 94 | C39: 74 | E39: https://www.4shared.com/web/preview/pdf/qV5PN6rbjq?
A40: https://www.scribd.com | B40: 45 | C40: 66 | E40: https://www.scribd.com/document/988715097/Investment-Strategies-for-Smart-Wealth-Creation-A-Complete-Guide-for-Modern-Investors?secret_password=HGoXcra7vHIMEqmaPFPm
A41: https://www.pdfhost.net/ | B41: 79 | C41: 62 | E41: https://www.pdfhost.net/index.php?Action=UploadFile
A42: 20/02/2026
A43: http://www.pinpdf.com/ | B43: 31 | C43: 37 | E43: https://pinpdf.com/best-investment-company-in-hyderabad-fc5ce9b3f2e8fc0e2f92aa3ce786cce4.html
A44: www.slideshare.net | B44: 94 | C44: 86 | E44: https://www.slideshare.net/slideshow/business-investors-in-hyderabad-investors-clubs/286144009
A45: dochub.com | B45: 60 | C45: 58 | E45: https://dochub.com/ritz-group/ALzmZB7wMmYGxJ7wX8J560/off-page-pdf
A46: issuu.com | B46: 94 | C46: 83 | E46: https://issuu.com/ritzgroup/docs/off_-_page_6a1bd94268ada7?cta=post-publish-view-live
A47: www.smallpdf.com | B47: 72 | C47: 57 | E47: https://smallpdf.com/edit-pdf#r=result&t=6c6259d5eabfeff68c82d59076faae08&i=annotate
A48: https://www.4shared.com/ | B48: 94 | C48: 74 | E48: https://www.4shared.com/web/preview/pdf/Bv1TXECdfa?
A49: https://www.scribd.com | B49: 45 | C49: 66 | E49: https://www.scribd.com/document/1000752085/Best-investment-company-in-hyderabad?secret_password=zr7r7eyF2D2L4ECT2Azs

Sheet Image Submissions
A1: Referring URl | B1: DA | C1: PA | D1: Type of Submission | E1: Submitted URl | F1: Status
A2: 46143
A3: https://www.photobucket.com/ | B3: 31 | C3: 37 | D3: Image | E3: https://www.photobucket.com/bucket/22e2f62a-5f5e-4ca3-a283-ed5745866671/media/ce7437a5-d684-4d02-a58e-20b99dae4da6 | G3: Gmail | H3: Password
A4: https://archive.org/ | B4: 94 | C4: 86 | D4: Image | E4: https://archive.org/details/entrepreneurs_202601 | G4: ritzgroupco123@gmail.com | H4: Ritzgroup@1122
A5: https://www.4shared.com/ | B5: 60 | C5: 58 | D5: Image | E5: https://www.4shared.com/account/home.jsp#dir=jZuwJ9pJ
A6: https://www.mediafire.com/ | B6: 94 | C6: 83 | D6: Image | E6: https://www.mediafire.com/file/hauxr78q4gphows/entrepreneurs.jpg/file
A7: https://www.dropbox.com/ | B7: 72 | C7: 57 | D7: Image | E7: https://www.dropbox.com/home?preview=entrepreneurs.jpg
A8: https://postimg.c | B8: 60 | C8: 58 | D8: Image | E8: https://postimg.cc/fSxXZtDJ
A9: https://myphoto.eu/ | B9: 32 | C9: 46 | D9: Image | E9: https://myphoto.eu/ritzgroupco123/photo/841218/investment.jpg
A10: https://app.parler.com/ | B10: 45 | C10: 62 | D10: Image | E10: https://app.parler.com/post/01ke73p9k1256tzbrcnxq1jwh9
A11: 46174
A12: https://www.imagevenue.com/ | B12: 24 | C12: 66 | D12: Image | E12: https://www.imagevenue.com/ME1C7N2W
A13: https://myphoto.eu/ | B13: 55 | C13: 87 | D13: Image | E13: https://myphoto.eu/ritzgroupco123/photo/841372/entrepreneurs.jpg
A14: https://ibb.co/album/ | B14: 77 | C14: 57 | D14: Image | E14: https://ibb.co/album/6rDBCP
A15: 46235
A16: https://myphoto.eu/ | B16: 55 | C16: 87 | D16: Image | E16: https://myphoto.eu/ritzgroupco123/photo/841634/ritz%20posts%20(2)%202.jpg
A18: 19/1/2026
A19: https://www.photobucket.com/ | B19: 31 | C19: 37 | D19: Image | E19: https://www.photobucket.com/bucket/22e2f62a-5f5e-4ca3-a283-ed5745866671/media/852252be-7417-49d7-aa56-c1000dc1c60d
A20: https://archive.org/ | B20: 94 | C20: 86 | D20: Image | E20: https://archive.org/details/untitled-design-6-1_202601
A21: https://www.4shared.com/ | B21: 60 | C21: 58 | D21: Image | E21: https://www.4shared.com/account/home.jsp#dir=jZuwJ9pJ
A22: https://www.mediafire.com/ | B22: 94 | C22: 83 | D22: Image | E22: https://www.mediafire.com/view/i8v3rusp62h05k6/550414511_122119365926963702_5189767811357890255_n.jpg/file
A23: https://www.dropbox.com/ | B23: 72 | C23: 57 | D23: Image | E23: https://www.dropbox.com/home?preview=Untitled+design+%286%29+%281%29.jpg
A24: https://app.parler.com/ | B24: 45 | C24: 62 | D24: Image | E24: https://app.parler.com/post/01kfayg5s78ha6t8jgkpvdxn69
A25: 22/1/2025
A26: https://www.photobucket.com/ | B26: 31 | C26: 37 | D26: Image | E26: https://www.photobucket.com/bucket/22e2f62a-5f5e-4ca3-a283-ed5745866671/media/f048f545-0422-4a03-9f5b-2bd137a3c649
A27: https://archive.org/ | B27: 94 | C27: 86 | D27: Image | E27: https://archive.org/details/ritz-community-post.jpg
A28: https://www.4shared.com/ | B28: 60 | C28: 58 | D28: Image | E28: https://www.4shared.com/account/home.jsp#dir=jZuwJ9pJ
A29: https://www.mediafire.com/ | B29: 94 | C29: 83 | D29: Image | E29: https://www.mediafire.com/view/2qy2fagd3ckie1l/Ritz_community_post.jpg.jpeg/file
A30: https://www.dropbox.com/ | B30: 72 | C30: 57 | D30: Image | E30: https://www.dropbox.com/home?preview=Ritz_community_post.jpg
A31: https://app.parler.com/ | B31: 45 | C31: 62 | D31: Image | E31: https://app.parler.com/post/01kfjpykatak5hvmqmpzmm9pfp
A32: https://myphoto.eu/ | B32: 55 | C32: 87 | D32: Image | E32: https://myphoto.eu/ritzgroupco123/photo/842796/Ritz_community_post.jpg.jpeg
A33: 28/1/2025
A34: https://www.photobucket.com/ | B34: 31 | C34: 37 | D34: Image | E34: https://www.photobucket.com/bucket/22e2f62a-5f5e-4ca3-a283-ed5745866671/media/c38d1cff-be1b-4b1b-8208-4ee85c958641
A35: https://archive.org/ | B35: 94 | C35: 86 | D35: Image | E35: https://archive.org/details/ritz-post-3.jpg
A36: https://www.4shared.com/ | B36: 60 | C36: 58 | D36: Image | E36: https://www.4shared.com/account/home.jsp#dir=jZuwJ9pJ
A37: https://www.mediafire.com/ | B37: 94 | C37: 83 | D37: Image | E37: https://www.mediafire.com/view/bglfutp1ue1ykz6/Ritz_post_%25283%2529.jpg.jpeg/file
A38: https://www.dropbox.com/ | B38: 72 | C38: 57 | D38: Image | E38: https://www.dropbox.com/home?preview=Ritz+post+%283%29.jpg.jpeg
A39: https://app.parler.com/ | B39: 45 | C39: 62 | D39: Image | E39: https://app.parler.com/ritzgroupco
A40: https://myphoto.eu/ | B40: 55 | C40: 87 | D40: Image | E40: https://myphoto.eu/ritzgroupco123/photo/843256/Ritz%20post%20(3).jpg.jpeg
A41: 46297
A42: https://www.photobucket.com/ | B42: 31 | C42: 37 | D42: Image | E42: https://www.photobucket.com/bucket/22e2f62a-5f5e-4ca3-a283-ed5745866671/media/986ddc77-b71d-4d14-a5c8-462fbd16e1ad
A43: https://archive.org/ | B43: 94 | C43: 86 | D43: Image | E43: https://archive.org/details/1-22_20260210_20260210
A44: https://www.4shared.com/ | B44: 60 | C44: 58 | D44: Image | E44: https://www.4shared.com/account/home.jsp#dir=jZuwJ9pJ
A45: https://www.mediafire.com/ | B45: 94 | C45: 83 | D45: Image | E45: https://www.mediafire.com/view/czsf7ujpj34a7st/1_22.jpg/file
A46: https://www.dropbox.com/ | B46: 72 | C46: 57 | D46: Image | E46: https://www.dropbox.com/home?preview=1+22.jpg
A47: https://app.parler.com/ | B47: 45 | C47: 62 | D47: Image | E47: https://app.parler.com/ritzgroupco
A48: https://myphoto.eu/ | B48: 55 | C48: 87 | D48: Image | E48: https://myphoto.eu/ritzgroupco123/photo/844568/1%2022.jpg
A49: 13/02/2026
A50: https://www.photobucket.com/ | B50: 31 | C50: 37 | D50: Image | E50: https://www.photobucket.com/bucket/22e2f62a-5f5e-4ca3-a283-ed5745866671/media/263c362b-8839-4a91-820b-abc07db4d268
A51: https://archive.org/ | B51: 94 | C51: 86 | D51: Image | E51: https://archive.org/details/ritz-posts-9.jpg-1
A52: https://www.4shared.com/ | B52: 60 | C52: 58 | D52: Image | E52: https://www.4shared.com/account/home.jsp#dir=jZuwJ9pJ
A53: https://www.mediafire.com/ | B53: 94 | C53: 83 | D53: Image | E53: https://www.mediafire.com/view/97rbsi0cpf9mdmv/Ritz_posts_%25289%2529.jpg_%25281%2529.jpeg/file
A54: https://www.dropbox.com/ | B54: 72 | C54: 57 | D54: Image | E54: https://www.dropbox.com/home?preview=Ritz+posts+%289%29.jpg+%281%29.jpeg
A55: https://myphoto.eu/ | B55: 55 | C55: 87 | D55: Image | E55: https://myphoto.eu/ritzgroupco123/photo/844898/Ritz%20posts%20(9).jpg%20(1).jpeg
A56: https://www.imagevenue.com/ | B56: 24 | C56: 66 | D56: Image | E56: https://www.imagevenue.com/ME1CDLP8
A57: https://ibb.co/album/ | B57: 77 | C57: 57 | D57: Image | E57: https://ibb.co/vCpWQk4n
A58: https://photos.shutterfly.com/ | B58: 54 | C58: 55 | D58: Image | E58: https://photos.shutterfly.com/full/1857011326583178
A59: 16/02/2026
A60: https://www.photobucket.com/ | B60: 31 | C60: 37 | D60: Image | E60: https://www.photobucket.com/bucket/22e2f62a-5f5e-4ca3-a283-ed5745866671/media/78aa2a63-157a-425b-8577-0581372a353a
A61: https://archive.org/ | B61: 94 | C61: 86 | D61: Image | E61: https://archive.org/details/555471970-122120153066963702-7613313594513986299-n
A62: https://www.4shared.com/ | B62: 60 | C62: 58 | D62: Image | E62: https://www.4shared.com/account/home.jsp#dir=jZuwJ9pJ
A63: https://www.mediafire.com/ | B63: 94 | C63: 83 | D63: Image | E63: https://www.mediafire.com/view/3mtbv1wpttuqlms/555471970_122120153066963702_7613313594513986299_n.jpg/file
A64: https://www.dropbox.com/ | B64: 72 | C64: 57 | D64: Image | E64: https://www.dropbox.com/home?preview=555471970_122120153066963702_7613313594513986299_n.jpg
A65: https://myphoto.eu/ | B65: 55 | C65: 87 | D65: Image | E65: https://myphoto.eu/ritzgroupco123/photo/845024/555471970_122120153066963702_7613313594513986299_n.jpg
A66: https://www.imagevenue.com/ | B66: 24 | C66: 66 | D66: Image | E66: https://www.imagevenue.com/ME1CDZZG
A67: https://ibb.co/album/ | B67: 77 | C67: 57 | D67: Image | E67: https://ritz-group.imgbb.com/albums
A68: https://photos.shutterfly.com/ | B68: 54 | C68: 55 | D68: Image | E68: https://photos.shutterfly.com/full/1857277158457737
A69: 19/02/2026
A70: https://www.photobucket.com/ | B70: 31 | C70: 37 | D70: Image | E70: https://www.photobucket.com/bucket/22e2f62a-5f5e-4ca3-a283-ed5745866671/media/2f4a4834-3cbc-4cef-8e1b-a9ca95a92a18
A71: https://archive.org/ | B71: 94 | C71: 86 | D71: Image | E71: https://archive.org/details/image_20260219_0949
A72: https://www.4shared.com/ | B72: 60 | C72: 58 | D72: Image | E72: https://www.4shared.com/file/IdZI7x7vge/image.html
A73: https://www.mediafire.com/ | B73: 94 | C73: 83 | D73: Image | E73: https://www.mediafire.com/view/5irjqvshcgk4mau/image.jfif/file
A74: https://www.dropbox.com/ | B74: 72 | C74: 57 | D74: Image | E74: https://www.dropbox.com/scl/fi/l7cdk08cdko1rl0ea1vwf/image-1.jfif?rlkey=qb4i38non9b506v2r10tg69r9&st=f4zqno50&dl=0
A75: https://myphoto.eu/ | B75: 55 | C75: 87 | D75: Image | E75: https://myphoto.eu/ritzgroupco123/photo/845444/image%20(1).jfif
A76: https://www.imagevenue.com/ | B76: 24 | C76: 66 | D76: Image | E76: https://myphoto.eu/ritzgroupco123/photo/845444/image%20(1).jfif

Sheet Business listing
A1: S.no | B1: Name | C1: Type of Submission | D1: Submitted URl | E1: Status
A2: 1 | B2: JustBazaar | C2: Business list | D2: https://www.justbazaar.in/index.php?route=account/account | F2: Gmail | G2: Password
A3: 2 | B3: gbusiness | C3: Business list | D3: https://www.gbusiness.co/user/business-category-details | F3: ritzgroupco123@gmail.com | G3: Ritzgroup@1122
A4: 3 | B4: apsense | C4: Business list | D4: https://www.apsense.com/account/dashboard
A5: 4 | B5: addyp | C5: Business list | D5: https://addyp.com/user/my-listings/
A6: 5 | B6: zoompo | C6: Business list | D6: https://www.zoompo.com/account/
A7: 6 | B7: freelistingindia | C7: Business list | D7: https://www.freelistingindia.in/listings/best-investment-company-in-india
A8: 8 | B8: whodoyou.com | C8: Business list | D8: https://www.freelistingindia.in/listings/best-investment-company-in-india-1
A9: 9 | B9: callupcontact | C9: Business list | D9: https://www.callupcontact.com/b/businessprofile/Ritzgroup/9915360
A10: 10 | B10: in.enrollbusiness | C10: Business list | D10: https://in.enrollbusiness.com/BusinessProfile/7675124/Ritzgroup
A11: 11 | B11: hub.biz | C11: Business list | D11: https://ritzgroup.hub.biz/
A12: 12 | B12: zumvu | C12: Business list | D12: https://zumvu.com/ritzgroupco/
A13: 13 | B13: bharathlisting | C13: Business list | D13: https://bharathlisting.com/user/my-listings/
A14: 14 | B14: trueen | C14: Business list | D14: https://trueen.com/business/listing/ritzgroup/684056
A15: 15 | B15: hotfrog | C15: Business list | D15: https://www.hotfrog.in/company/e1fd8cf9de004a0b141570cebc375317
... A24: 27 | B24: https://postlister.com/ | C24: Business list | D24: https://postlister.com/

Sheet Ritz Reports
A1: Month | B1: SEO Keyword Ranking | C1: SEO Offline | D1: Web Optimization | E1: E Mail Marketing | F1: Google Business Profile | G1: Google Codes | H1: Competitive Analysis | I1: Google Ad Campaigns | J1: Meta Ad Campaigns | K1: Technical SEO | L1: DA | M1: PA | N1: Back Link | O1: Total Submssions | P1: Blogs
A2: November - December | B2: Done | C2: On Going | D2: Done | E2: On Going | F2: NO | G2: G- Tag Implmented - Live | H2: Done | I2: NO | J2: NO | K2: On Going | L2: 0 | M2: 0 | N2: 0 | O2: 0 | P2: 1 - Publishing
A3: December - January | B3: Done | C3: On Going | D3: Done | E3: On Going | F3: NO | G3: G- Tag Implmented - Live | H3: Done | I3: NO | J3: NO | K3: On Going | L3: 1 | M3: 8 | N3: 374 | O3: 374 | P3: Pending
A4: January - February | B4: Done | C4: On Going | D4: Done | E4: On Going | F4: Done | G4: G- Tag Implmented - Live | H4: Done | I4: NO | J4: NO | K4: On Going | L4: 6 | M4: 13 | N4: 434 | O4: 434 | P4: Pending

Sheet Investor & Investments
B1: Investor and Investment urls facebook | C1: Members | E1: Top 10 Investment Pages on Meta (Facebook & Instagram)
B2: https://www.facebook.com/groups/1061653300532134 | C2: 6.9K | L2: Top 10 Investor Communities & Groups on LinkedIn
B3: https://www.facebook.com/groups/297419747028527 | C3: 25.4 K | E3: 1. Moneycontrol | L3: 1. Private Equity, M&A & Venture Capital Investments Group
B4: https://www.facebook.com/groups/554878631377940 | C4: 77.3K | E4: 2. CNBC TV18 | L4: A large group focused on private equity, mergers & acquisitions, venture capital trends, fundraising, and investing discussions great for institutional and startup dealmakers.
B5: https://www.facebook.com/groups/721944231933660 | C5: 28.8K | E5: 3. ET Markets | L5: 2. International Wealth Management Group
B6: https://www.facebook.com/groups/824513894623173 | C6: 20.8K | E6: 4. Zerodha Varsity | L6: Connects investors, wealth advisors, and finance professionals with discussions on asset management, investment strategies, and opportunities. (Startup Funding Espresso)
B7: https://www.facebook.com/groups/304863384453580 | C7: 18.4K | E7: 5. Groww | L7: 3. Angel Investors Network (AIN)
B8: https://www.facebook.com/groups/461024814081503 | C8: 2.4K | E8: 6. Investopedia | L8: A community of angel investors and experienced backers sharing opportunities, trends, co-investment ideas, and private equity news. (LinkedIn)
B9: https://www.facebook.com/groups/6106028739484683 | C9: 12.3K | E9: 7. Bloomberg | L9: 4. Investment & Fundraising Group
B10: https://www.facebook.com/groups/realestatehyderabad | C10: 6.9K | E10: 8. Value Research Online | L10: General group for investors and entrepreneurs to discuss funding strategies, startup investing, and capital raising. (LinkedIn)
B11: https://www.facebook.com/groups/128698827173195 | C11: 95.2K | E11: 9. The Motley Fool | L11: 5. Global Hedge Fund & Alternative Investments Network
B12: https://www.facebook.com/groups/2723735614532955 | C12: 13.8K | E12: 10. TradingView | L12: A professional group for hedge fund professionals and alternative investment practitioners (quant funds, hedge strategies, risk mgmt). (MoneyScience)
B13: https://www.facebook.com/groups/writetoclubunlimit | C13: 49.0K | L13: 6. Quantitative Finance Network
B14: https://www.facebook.com/groups/362798909269774 | C14: 78.7K | L14: Focused on investment strategies using quantitative and algorithmic models, machine learning, risk assessment, and research useful for data-driven investors. (MoneyScience)
B15: https://www.facebook.com/groups/investmentopportunityindia | C15: 18.4K | L15: 7. The QUANTS Network
B16: https://www.facebook.com/groups/882327789292969 | C16: 9.9K | L16: Dedicated to quantitative analysts, traders, and strategic investors who use advanced math and modelling for portfolio construction and markets. (MoneyScience)
B17: https://www.facebook.com/groups/1802837446958441 | C17: 22.1K | L17: 8. Family Offices Group
L18: A LinkedIn community where family office professionals, wealth managers, and private investors share high-net-worth investing trends and deal flow. (MoneyScience)
L19: 9. Startup & Investment Ecosystem Network
B20: Top Investor Communities & Groups in Hyderabad | L20: For founders, angel investors, and VCs — focuses on startup investing, scaling, pitch feedback, fundraising strategies, and mentorship. (startupcouncil.org)
B21: 1. Hyderabad Angels | C21: I | L21: 10. Venture Capital & Startup Funding Community
B22: Hyderabad Angels - Startup Investors in India Web Address: Plot No 18, iLabs Centre, Ground Floor, Building 3, Software Units Layout, Madhapur, Telangana 500081, India Phone: +914040484444 | L22: A group where venture capital professionals and active investors comment on emerging trends, share portfolios, and connect with founders. (Startup Funding Espresso)
B23: Active angel investor network that invests in early-stage startups and connects founders with seasoned investors. It regularly hosts pitch events, demo days, and investor meetups. (hyderabadangels.in)
B24: 2. Biz Innings
B25: Biz Innings - Venture Capital Funding Web Address: 8th Floor, Regus Grandeur, SLN Terminus, Survey No 133, Gachibowli - Miyapur Rd, Golden Habitat, Whitefields, Gachibowli, Hyderabad, Telangana 500032, India Phone: +919618141109
B26: Venture capital-focused firm in Hyderabad that helps startups connect with venture capital funding, angel investors, and government grants. Good for founders and investors looking for funding channels and networking. (bizinnings.com)
B27: 3. Venture Capital and Corporate Investments Private Limited
B28: Venture Capital and Corporate Investments Private Limited Web Address: 4th & 5th Floors, Plot No.57, II AURUM” Door No. 4-50/P-11/57/4f & 5f, Jayabheri Enclave, Gachibowli, Hyderabad, Telangana 500032, India Phone: +914023818475
B29: Investment and VC company in Hyderabad connecting corporates, startups, and investors — useful as a community contact point to meet early-stage investors.
B30: 4. Startup Grind Hyderabad
B31: A chapter of the global startup community that regularly hosts events where founders, investors, and ecosystem builders connect, share ideas, and network. Great for meeting local angels and VC representatives. (startupgrind.com)
B32: 5. eChai Hyderabad Startup Network
B33: A vibrant local community that runs regular meetups for entrepreneurs, investors, and ecosystem partners, offering informal networking and pitches. (Meetup)
B34: 6. Primewise Founders Club Hyderabad
... B43: While not a single group, Hyderabad regularly hosts investor-startup forums, summits, and investor dinner networking meetups where active investors, founders, and ecosystem partners meet and collaborate useful to join via Eventbrite or Meetup. (Eventbrite)
B45: Projects | C45: Urls | D45: States
B46: Prakrit | C46: https://prakrit.co/ | D46: Done
B47: Ritzgroup | C47: https://ritzgroup.co/ | D47: Done
B48: Cosmos | C48: https://cosmosclinics.in/ | D48: Done
B49: Healthion | C49: https://healthion.in/ | D49: Done
B52: youtube investor and investment Videos | C52: Views
B53: https://www.youtube.com/watch?v=yjBjpUp31pA | C53: 7.6 Views
B54: https://www.youtube.com/watch?v=6Gbm-OHOb8A | C54: 436 Views | D54: Explore emerging niche markets in 2023 with our Investors at Family Office Club!
B55: https://www.youtube.com/shorts/Ug8jA3374oI
B56: https://www.youtube.com/shorts/D5ZIp3zl-hc
B57: https://www.youtube.com/shorts/p65-3IFFk40 | C57: 9.1K Views | D57: Your 30 seconds should feel like a spark a story that turns a real-world pain point into an inevitable opportunity.
B58: https://www.youtube.com/watch?v=IK7HkSp1KBI&t=451s | C58: 12K Views
B59: https://www.youtube.com/watch?v=l0hBGHQaglE | C59: 776 Views
B60: https://www.youtube.com/shorts/evbdTwDGI1Y

Sheet social media channels.
A1: Social Media Channels. | B1: Channels | D1: Date - 06/02/2026 | G1: Platform | H1: Post Size | I1: Story/Reel | J1: Cover/Banner
A2: Urls | D2: Followers | G2: Facebook | H2: 1080×1080 | I2: 1080×1920 | J2: 820×312
A3: https://www.linkedin.com/company/ritzgroupco | B3: Linkdeln | D3: 23 | G3: Instagram | H3: 1080×1350 | I3: 1080×1920 | J3: —
A4: https://www.instagram.com/ritz_groupco/# | B4: Instagram | D4: 48 | G4: X | H4: 1600×900 | I4: — | J4: 1500×500
A5: https://www.facebook.com/ritzgroupco | B5: Facebook | D5: 10 | G5: LinkedIn | H5: 1200×1200 | I5: — | J5: 1584×396
A6: https://www.youtube.com/@ritzgroupco | B6: Youtube | D6: 26 subscribers | G6: YouTube | H6: 1280×720 | I6: 1080×1920 | J6: 2560×1440
A7: https://x.com/ritzgroupco | B7: X | D7: 3
B10: Social media platfrom
A11: top 5 company in india | B11: Facebook | C11: followrs | D11: instagram | E11: followrs | F11: linedin | G11: followrs | H11: youtube | I11: followrs | J11: x | K11: followrs | M11: Keywords
A12: https://www.blackstone.com/ | B12: https://www.facebook.com/blackstone | C12: 42K followers | F12: https://www.linkedin.com/company/blackstoneinc/ | G12: 2M followers | H12: No | J12: https://x.com/blackstone | K12: 154.4K Followers
A13: https://www.kkr.com/ | F13: https://www.linkedin.com/company/kkr/ | G13: 803K followers | H13: https://www.youtube.com/@kohlbergkravisroberts | I13: 4.21K subscribers | J13: https://x.com/kkr_co | K13: 34.4K Followers
A14: https://www.carlyle.com/ | D14: https://www.instagram.com/onecarlyle/ | E14: 20K followers | F14: https://www.linkedin.com/company/the-carlyle-group/ | G14: 533K followers | H14: https://www.youtube.com/onecarlyle | I14: 3.74K subscribers
A15: https://www.baincapital.com/ | F15: https://www.linkedin.com/company/bain-capital/ | G15: 412K followers | J15: https://x.com/baincapital?lang=en | K15: 14.3K Followers
A16: https://www.avendus.com/india | F16: https://www.linkedin.com/company/avendus/ | G16: 149K followers | H16: https://www.youtube.com/@SingaporeEDB | I16: 3.5K subscribers | J16: https://x.com/Avendus | K16: 2,901 Followers
A19: https://www.gic.com.sg/ | D19: https://www.instagram.com/gicsg/ | E19: 17.6K followers | F19: https://www.linkedin.com/organization-guest/company/gic | H19: https://www.youtube.com/user/GICsingaporevideos/featured | I19: 3.23K subscribers
A20: https://www.investcorp.com/ | D20: https://www.instagram.com/investcorp/?hl=en | E20: 5,485 followers | F20: https://www.linkedin.com/company/investcorp/ | G20: 63K followers | H20: https://www.youtube.com/channel/UCyyXRFacgErKoYM7syRkXZQ | I20: 1.87K subscribers | J20: https://x.com/Investcorp | K20: 5,907 Followers
A21: https://www.blackrock.com/sg | M21: Investment Management & Financial Services | BlackRock
A22: https://eservices.mas.gov.sg/ | F22: https://www.linkedin.com/company/mas | G22: 176K followers | H22: https://www.youtube.com/MASsingapore | I22: 4.85K subscribers | J22: https://x.com/mas_sg | K22: 34.5K Followers
A23: https://www.edb.gov.sg/ | B23: https://www.facebook.com/EDBsg/ | C23: 82K followers | D23: https://www.instagram.com/singapore_edb/ | E23: 3,676 followers | F23: https://www.linkedin.com/company/singapore-economic-development-board/ | G23: 168K followers | H23: https://www.youtube.com/@SingaporeEDB | I23: 3.5K subscribers
A24: https://www.01vc.com/en/ | F24: https://www.linkedin.com/company/01vc/ | G24: 2K followers
A25: https://www.temasek.com.sg/en/index | B25: https://www.facebook.com/temasekholdings | C25: 61K followers | F25: https://www.linkedin.com/company/temasek-holdings/?originalSubdomain=sg | G25: 214K followers | H25: https://www.youtube.com/user/TemasekDigital | I25: 26K subscribers
A26: https://ensun.io/ | B26: https://www.facebook.com/ensungmbh | C26: 624 followers | F26: https://www.linkedin.com/company/ensun-gmbh/ | G26: 3K followers | H26: https://www.youtube.com/channel/UCaao7m7vTabbZ4nbiHlYQAw | I26: 123 subscribers
A27: https://www.eastspring.com/my | B27: https://www.facebook.com/EastspringMY | C27: 29K followers | F27: https://www.linkedin.com/company/eastspring-investments/ | G27: 64K followers
A28: https://www.khazanah.com.my/ | F28: https://www.linkedin.com/company/khazanah-nasional/ | G28: 202K followers | H28: https://www.youtube.com/@khazanahnasionalberhad | I28: 1.72K subscribers
A30: top 5 company in US
A31: https://sequoiacap.com/
A32: https://a16z.com/
A33: https://www.accel.com/ | F33: https://www.linkedin.com/company/accel-vc/ | G33: 316K followers | H33: https://www.youtube.com/@AccelVC | I33: 26.5K subscribers | J33: https://x.com/accel | K33: 269.5K Followers
A34: https://www.nea.com/ | F34: https://www.linkedin.com/company/new-enterprise-associates/ | G34: 74K followers | H34: https://www.youtube.com/channel/UCTU3mQDqk3QyB4WeDQwZ1YQ | I34: 313 subscribers | J34: https://x.com/NEA | K34: 75.5K Followers
A35: https://www.bvp.com/ | F35: https://www.linkedin.com/company/bessemer-venture-partners/ | G35: 221K followers | H35: https://www.youtube.com/c/bessemerventurepartners | I35: 5.21K subscribers | J35: https://x.com/bessemervp | K35: 108.2K Followers
A37: top 5 company in UK
A38: https://atomico.com/ | F38: https://www.linkedin.com/company/atomico/ | G38: 76K followers | H38: https://www.youtube.com/@atomico | I38: 593 subscribers
A39: https://www.indexventures.com/ | F39: https://www.linkedin.com/company/index-ventures/ | G39: 189K followers | J39: https://x.com/indexventures | K39: 111.8K Followers
A40: https://www.balderton.com/ | F40: https://www.linkedin.com/company/balderton/ | G40: 88K followers | J40: https://x.com/balderton | K40: 45.5K Followers
A41: https://dcpla.com/ | F41: https://www.linkedin.com/organization-guest/company/dc-placement-advisors?challengeId=AQFTuqKzomQkIwAAAXNwssn499PpqTwhIi12R5NmntwayB2jqA8KkvZEuJYFHtFDAlE87k6dgBKqhGtKoN_cn-hd9Mn0QqhOYw&submissionId=0ef5ca11-64ba-2316-ce08-6419cea2c773 | G41: 761 followers
A42: https://seedcamp.com/
A44: https://waterfieldadvisors.com/ | D44: https://www.instagram.com/waterfieldadvisors/ | E44: 2,039 followers | F44: https://www.linkedin.com/company/waterfieldadvisors/ | G44: 28K followers | H44: https://www.youtube.com/channel/UCh8zCouqoupmt9EYVqfI1Nw | I44: 4.26K subscribers | J44: https://x.com/WInsights_WFA | K44: 547 Followers

Sheet website Aduit
A1: S.NO | B1: Type | C1: Url | D1: Existing Title | E1: Keyword | F1: Existing Descritions | G1: Meta Title | H1: Meta Descriptions | I1: suggested primar keyword | J1: suggested secondary keyword | K1: Alttags | L1: H1 | M1: H2 | N1: H3 | O1: H4 | P1: H5 | Q1: H6
A2: 1 | B2: Home | C2: https://ritzgroup.co/ | D2: Invest with Purpose Grow with Best Investment Companies in India | E2: Top Investment & Asset Management Companies in Hyderabad | F2: Ritz Group – Best Investment Company in India offering Venture Capital, Fund Management, Investors Club, and Micro & Macro Investment services. | G2: Best Investment Company in India | Ritz Group | H2: Ritz Group – Best Investment Company in India offering Venture Capital, Fund Management, Investors Club, and Micro & Macro Investment services. | K2: Done | L2: Invest with Purpose Grow with Best Investment Companies in India | M2: : About Ritzgroup <H2>: Why Choose Ritz Group <H2>: <H2>: Frequently asked questions | N2: Investors Club <H3>: Micro Macro Investments <H3>: Venture Capital <H3>: Fund Management <H3>: Ritz Group Introduces Terranova Project: A World-Class Natures Luxury Shaping the Future of Living <H3>: RITZ WEALTH CLUB | O2: As one of the best investment companies in India , Ritz Group’s ecosystem <H4>: Location : PARK HYATT - HYDERABD | P2: Follow us
A3: 2 | B3: About - us | C3: https://ritzgroup.co/about-us | D3: Ritz Group – About Green, Finance & Health Investments | F3: Ritz Group – About Green, Finance & Health Investments. We specialize in GreenTech, FinTech, and HealthTech investments driving innovation, growth, and sustainability. | G3: Ritz Group – About Green, Finance & Health Investments | H3: Ritz Group – About Green, Finance & Health Investments. We specialize in GreenTech, FinTech, and HealthTech investments driving innovation, growth, and sustainability. | K3: NO | L3: About us | M3: Who We Are | P3: Follow us
A4: 3 | B4: Projects | C4: https://ritzgroup.co/projects | D4: Ritz Group – GreenTech, FinTech & HealthTech Investments | F4: Ritz Group – GreenTech, FinTech & HealthTech Investments offers innovative, sustainable, and high-return investment opportunities across emerging sectors. | G4: Ritz Group – GreenTech, FinTech & HealthTech Investments | H4: Ritz Group – GreenTech, FinTech & HealthTech Investments offers innovative, sustainable, and high-return investment opportunities across emerging sectors. | K4: NO | L4: Projects | M4: Building the Future with Focused Investments. <H2>: Terranova <H2>: FinTech <H2>: Health Tech <H2>: Fashion Lifestyle | P4: Follow us
A5: 4 | B5: Services | C5: https://ritzgroup.co/venture-capital | D5: Top Venture Capital Firms in India 2025 | Ritz Group | E5: Top 10 Venture Capital Firms in India - List of Venture Capital Firms | Top Angel Networks for Indian Startups | F5: Discover why Ritz Group ranks among the top venture capital firms in India 2025, empowering startups with expert fund management, private equity, and investment growth. | G5: Top Venture Capital Firms in India 2025 | Ritz Group | H5: Discover why Ritz Group ranks among the top venture capital firms in India 2025, empowering startups with expert fund management, private equity, and investment growth. | K5: Done | L5: Top Venture Capital Firm in India. | M5: Venture Capital <H2>: Driving innovation as a top venture capital firm in India. <H2>: Frequently asked questions | N5: What We Offer <H3>: Why Join Us <H3>: Exclusive Deal Access <H3>: Strong Network <H3>: Beyond Capital Support <H3>: Global Reach <H3>: Future-Value | P5: Investment in High-Potential Start-ups <H5>: Strategic Mentorship Advisory <H5>: Extensive Industry Network <H5>: Technology Growth Enablement <H5>: Long-Term Value Creation <H5>: <H5>: Follow us
C6: https://ritzgroup.co/fund-management | D6: Fund Management services in India - Ritz Group | E6: Best Asset Management Company in India | F6: Ritz Group stands among Fund Management services in India, offering expert fund management, portfolio growth, and venture capital solutions. | G6: Fund Management services in India - Ritz Group | H6: Ritz Group stands among Fund Management services in India, offering expert fund management, portfolio growth, and venture capital solutions. | K6: Done | L6: Fund Management services in India | M6: Fund Management <H2>: Future-Ready, High-Return Portfolio Solutions in Fund Management India <H2>: Why Join Us | N6: What We Offer | P6: Diversified Portfolio Management <H5>: Data-Driven Investment Decisions <H5>: Risk-Adjusted Return Strategies <H5>: Strong Governance Transparency <H5>: Performance-Focused Management <H5>: <H5>: <H5>: Follow us
C7: https://ritzgroup.co/investors-club | D7: Business Investors in India | Investors Clubs | E7: List of Angel Investors for Indian Startup Companies | F7: Discover leading business investors in India and exclusive investors clubs by Ritz Group, offering startup funding, venture capital, and investment growth. | G7: Business Investors in India | Investors Clubs | H7: Discover leading business investors in India and exclusive investors clubs by Ritz Group, offering startup funding, venture capital, and investment growth. | K7: Done | L7: B usiness Investors in India | M7: Investors Club <H2>: Exclusive Network for Business Investors In India <H2>: Frequently asked questions | N7: What We Offer <H3>: Collaborative Growth <H3>: Borderless Opportunities <H3>: Continuous Learning | P7: Exclusive Investment Access <H5>: Strategic Networking Collaboration <H5>: Global Market Connectivity <H5>: Knowledge Insight Programs <H5>: <H5>: Follow us
C8: https://ritzgroup.co/micro-and-macro-investment | D8: Micro & Macro Investments in India | RitzGroup | F8: Explore smart micro and macro investment opportunities in India with RitzGroup. Start small, grow steadily, and secure your financial future expert guidance. | G8: Micro & Macro Investments in India | RitzGroup | H8: Explore smart micro and macro investment opportunities in India with RitzGroup. Start small, grow steadily, and secure your financial future expert guidance. | K8: Done | L8: Micro Macro Investments | M8: Micro Macro Investments <H2>: Empowering Ideas of Every Scale | N8: What We Offer <H3>: Market-Aligned Planning | P8: <H5>: Micro Investments <H5>: Macro Investments <H5>: <H5>: Follow us
A10: 5 | B10: Membership | C10: https://ritzgroup.co/membership/investors | D10: Explore Membership | RitzGroup | F10: NO | G10: Explore Membership | RitzGroup | H10: NO | K10: 3 images without ALT. | L10: Investors Membership | M10: <H2>: SILVER CLUB <H2>: GOLD CLUB <H2>: DIAMOND CLUB | P10: <H5>: What You Get <H5>: Fees <H5>: What You Get <H5>: Dedicated Services <H5>: Fees <H5>: What You Get <H5>: Dedicated Services <H5>: Fees <H5>: Upgrade Membership <H5>: <H5>: Follow us
C11: https://ritzgroup.co/membership/entrepreneurs | D11: Explore Membership | RitzGroup | F11: NO | G11: Explore Membership | RitzGroup | H11: NO | K11: 3 images without ALT. | L11: Entrepreneurs Membership | M11: : Launch Pad <H2>: Growth Accelerator <H2>: Capital Partner | P11: <H5>: What You Get <H5>: Fees <H5>: What You Get <H5>: Fees <H5>: What You Get <H5>: Fees <H5>: Upgrade Membership <H5>: <H5>: Follow us
A13: 6 | B13: Resources | C13: https://ritzgroup.co/blog | D13: Blog Posts | RitzGroup | F13: NO | G13: Blog Posts | RitzGroup | H13: NO | K13: 3 images without ALT. | P13: Blogs <H5>: <H5>: Follow us
C14: https://ritzgroup.co/jobs | D14: Jobs | RitzGroup | F14: NO | G14: Jobs | RitzGroup | H14: NO | K14: 4 images without ALT. | L14: Our Job Offers | P14: <H5>: Follow us <H5>: <H5>: Follow us
A16: 7 | B16: Contactus | C16: https://ritzgroup.co/contactus | D16: Contact Us | RitzGroup | F16: NO | G16: Contact Us | RitzGroup | H16: NO | K16: 3 images without ALT. | L16: : Contact us | P16: Follow us
A18: 8 | B18: Register | C18: https://ritzgroup.co/register/investment | D18: Registration - Ritz Investment | F18: NO | K18: DONE | L18: Registration | M18: : Verify Your Mobile Number <H2>: KYC Verification Required? <H2>: Are You Sure? | N18: <H3>: Personal Information <H3>: Security Information <H3>: Verify Mobile Number

Sheet Competitor Keywords
A1: Primary Competitor Keywords | B1: Competitor website Urls Hyderabad | C1: Competitor website Urls India | D1: Image Alt tag | E1: Home page keywords competitor keywords
B2: https://www.glassdoor.co.in/ | C2: https://www.glassdoor.co.in/ | D2: About us | E2: Top Investment & Asset Management Companies in Hyderabad
A3: Best Investment Company in India | B3: https://www.gcia.in/ | C3: https://www.aequitasindia.in/ | D3: Ritz group vision | E3: Guardian Capital Investment Advisors Hyderabad, India
A4: Top Venture Capital Firms in India | B4: https://clutch.co/in/funding-investment/hyderabad | C4: https://www.avendus.com/india/wealth-management | D4: Ritz group mission | E4: Top wealth management and advisory firm in India
A5: Startup Funding Companies in India | B5: https://hyderabadangels.in/ | C5: https://www.lusha.com/ | D5: Ritz group
A6: Business Investors in India | B6: https://www.plumhq.com/blog/vcs-and-investors-in-hyderabad | C6: https://www.edzeb.com/ | D6: Project
A7: Angel Investors Network India | B7: https://mentormecareers.com/ | C7: https://www.investindia.gov.in/ | D7: Terranova Project - Ritz group
A8: Investment Management Company India | C8: https://groww.in/ | D8: FinTech Project - Ritz group
A9: Private Equity Firms in India | D9: Health Tech Project - Ritz group
A10: Fund Management Services in India | D10: Fashion & Lifestyle Project - Ritz group
A11: Startup Investment Platform India | D11: Membership
A12: Investor Network for Startups | D12: Resource
D13: Contactus
A14: Secondary Competitor Keywords
A15: Early Stage Startup Funding India
A16: Seed Funding for Startups India
A17: Growth Capital Investors India
A18: Micro Investment Opportunities India
A19: Macro Investment Strategies India
A20: Alternative Investment Firms India
A21: Investment Clubs in India
A22: Startup Mentorship & Funding
A23: Equity Investment Firms India
A24: Business Expansion Funding India
A26: Long-Tail Competitor Keywords
... A34: Private investors for business expansion
A36: Home page | B36: Internal Links
A37: top investment companies in India | B37: Contact Us
A38: Best investment company in india | B38: Top Venture Capital Firms in India
A39: Services
A40: Top Venture Capital Firms in India | B40: Home page
A41: Fund Management services in India | B41: Home page
A42: business investors in India, | B42: Home page
A43: Investment opportunities | B43: Contact Us
A44: Micro & Macro Investments in India | B44: Top Venture Capital Firms in India
B46: Learn more - aboutus buttons not working
B47: Learn more buttons change to Registration

Sheet Sheet1
